Workbook

Sheet 00_Instructions
A1: CONTINUOUS AUDIT & LOSS PREVENTION: POS CASHIER & TILL FRAUD DETECTION MANUAL
A2: OPERATIONAL SOP: Standard Operating Procedure, POS Data Ingestion Protocols, and Surveillance Review Standards for Audit Teams
A3: Target Scope: Multi-Unit Retail, Food & Beverage, Quick-Service Restaurants | Framework: IIA Continuous Auditing & Monitoring Standards | Version: 2.0
A5: Operational Focus / Step | B5: Field Audit Procedure & Evidentiary Protocol
A6: SECTION 1: OBJECTIVE | B6: 1. AUDIT OBJECTIVE & OPERATIONAL CONTEXT
A7: Operational Context & Till Balancing Limitation | B7: Standard end-of-shift drawer reconciliations confirm only that physical currency matches net recorded POS sales. Cashier misappropriation occurs upstream in the transaction lifecycle by suppressing the record of sale—specifically through post-settlement voids, pre-settlement line item deletions, or unrecorded drawer openings—leaving the register balanced to the penny while currency is diverted.
A8: Electronic Journal (EJ) Transaction Logs | B8: Modern POS systems maintain an append-only Electronic Journal (EJ) recording all terminal events, drawer openings, and supervisory authorizations. Procedural violations leave distinct audit trails: extended latency between ticket opening and cancellation, disproportionate cash tender ratios, and supervisory credential concurrency across separate workstations.
A9: SECTION 2: WORKFLOW | B9: 2. AUDIT PROCEDURE & OPERATING CHECKLIST
A10: Phase 1: Extraction | B10: Export 7 to 30 days of raw POS event logs in CSV format from the POS back-office system. Consult '01_POS_Data_Spec' for system-specific report navigation paths and field mapping schemas (Oracle Micros, NCR Aloha, Toast, Revel, Square).
A11: Phase 2: Master Setup | B11: Open '02_Cashier_Register'. Verify that active cashier rosters, branch terminal assignments, and store baseline parameters (expected cash tender %, normal void rate %, and no-sale drawer benchmark) reflect current operating standards.
A12: Phase 3: Ingestion | B12: Open '03_Raw_POS_Journal'. Populate raw POS transactional data into Columns A through M (Navy Headers #1F4E78) using Paste Special > Values. Preserve Columns N and O (Steel Blue Headers #2F5597), which contain automated calculation formulas for event latency and exception flags.
A13: Phase 4: Analysis | B13: Review calculation tabs '04_Engine_Voids', '05_Engine_Drawer_Kicks', and '06_Engine_Overrides'. The workbook calculates cashier Z-scores, void latency intervals, excess drawer openings, and supervisory authorization concentration without manual formula adjustment.
A14: Phase 5: Risk Prioritization | B14: Open '99_Investigator_Dashboard'. Identify cashiers exhibiting Composite Risk Scores >= 65 (Critical/High Risk) or flagged for supervisory authorization anomalies ('WATCHLIST / HIGH COLLUSION'). Prioritize these personnel for detailed transaction testing.
A15: Phase 6: Video Corroboration | B15: Extract incident timestamps from Table 2 ('Targeted Video Surveillance Review Queue') on '99_Investigator_Dashboard'. Request targeted 5-minute surveillance footage from Loss Prevention / Security to verify physical transaction events prior to administrative follow-up.
A16: SECTION 3: DATA EXTRACTION | B16: 3. POS SYSTEM DATA EXTRACTION PROCEDURES
... A43: [SOFT RED HIGHLIGHTS #FADBD8] | B43: Exception & Risk Flags. Identifies transactions, cashiers, and supervisory accounts exceeding statistical anomaly thresholds.

Sheet 01_POS_Data_Spec
A1: POS SYSTEM FIELD MAPPING & DATA INGESTION SPECIFICATION
A2: OPERATIONAL GUIDANCE: Map extracted POS transaction journal fields to the standardized model parameters below prior to pasting into 03_Raw_POS_Journal.
A4: Model Field Name | B4: Required Format | C4: Description | D4: Oracle Micros Simphony | E4: NCR Aloha | F4: Toast POS | G4: Revel Systems | H4: Square POS
A5: Event_ID | B5: Text (Alpha-Num) | C5: Unique event identifier from POS transaction journal | D5: trans_dtl_seq | E5: EVENT_ID | F5: Event ID | G5: event_id | H5: Event ID
A6: Transaction_ID | B6: Text (Alpha-Num) | C6: Guest check, receipt, or order reference number | D6: check_seq | E6: CHECK_NUM | F6: Order # | G6: order_id | H6: Payment ID
A7: Event_Timestamp | B7: YYYY-MM-DD HH:MM:SS | C7: Exact date and time the POS event was recorded | D7: trans_dtl_tm | E7: SYSTEM_TIME | F7: Opened Time | G7: created_date | H7: Date Time
A8: Branch_ID | B8: Text / Code | C8: Store, restaurant, or site location code | D8: store_num | E8: STORE_ID | F8: Location Code | G8: establishment_id | H8: Location
A9: Terminal_ID | B9: Text / Code | C9: Workstation, register, or tablet terminal identifier | D9: rvc_seq | E9: TERM_ID | F9: Device Name | G9: pos_station_id | H9: Device ID
A10: Cashier_ID | B10: Text / Code | C10: Employee ID currently authenticated on terminal | D10: emp_seq | E10: EMP_ID | F10: Server / Cashier ID | G10: user_id | H10: Employee ID
A11: Supervisor_PIN | B11: Text / Code | C11: Manager or supervisor authorizing void or override | D11: mgr_auth_seq | E11: AUTH_MGR_ID | F11: Manager Override User | G11: authorized_by | H11: Approver ID
A12: Event_Type | B12: Category Text | C12: Event classification (Sale Tender, Post-Bill Void, Line Item Void, No-Sale Drawer Opening) | D12: trans_type_desc | E12: TYPE_NAME | F12: Order Event | G12: type | H12: Event Type
A13: Tender_Type | B13: Category Text | C13: Payment method: Cash, Card, Delivery Aggregator, or N/A | D13: tender_media_name | E13: TENDER_NAME | F13: Payment Method | G13: payment_type | H13: Tender Type
A14: Item_Count | B14: Integer | C14: Number of distinct items on ticket or line voided | D14: item_cnt | E14: QTY | F14: Total Items | G14: line_count | H14: Quantity
A15: Gross_Amount | B15: Currency ($) | C15: Original ticket or item amount before discounts/voids | D15: gross_sales_amt | E15: SUB_TOTAL | F15: Item Amount | G15: gross_amount | H15: Gross Sales
... A17: Order_Start_Time | B17: YYYY-MM-DD HH:MM:SS | C17: Timestamp when check was initially opened / first item scanned | D17: check_open_tm | E17: OPEN_TIME | F17: Order Created At | G17: opened_date | H17: Check Opened

Sheet 02_Cashier_Register
A1: BRANCH BENCHMARKS & CASHIER REGISTRATION DIRECTORY
A2: DATA INPUT & CONFIGURATION: Maintain branch baseline parameters (Rows 5-9) and active cashier roster (Rows 13-28). Blue headers (#1F4E78) designate user-configurable inputs.
A4: BRANCH OPERATING BASELINES & CONTROL THRESHOLDS
A5: Branch ID | B5: Branch Location Name | C5: Total Terminals | D5: Expected Cash % | E5: Normal Void % | F5: No-Sale Benchmark (per 100 Txs)
A6: BR-01 | B6: Downtown Flagship | C6: 4 | D6: 0.35 | E6: 0.018 | F6: 2
A7: BR-02 | B7: Mall Concourse | C7: 4 | D7: 0.4 | E7: 0.021 | F7: 2.5
A8: BR-03 | B8: Airport Terminal 2 | C8: 3 | D8: 0.25 | E8: 0.015 | F8: 1.8
A9: BR-04 | B9: Business Bay Express | C9: 2 | D9: 0.3 | E9: 0.019 | F9: 2.2
A12: ACTIVE CASHIER & WORKSTATION DIRECTORY
A13: Cashier ID | B13: Cashier Full Name | C13: Assigned Branch | D13: Terminal Default | E13: Shift Assignment | F13: Hire Date | G13: Audit Status
A14: C-101 | B14: Marcus Vance | C14: BR-01 | D14: T-01 | E14: Morning | F14: 2024-03-15 | G14: Active
A15: C-102 | B15: Elena Rostova | C15: BR-01 | D15: T-02 | E15: Evening | F15: 2023-11-01 | G15: Active
A16: C-103 | B16: Tariq Mansour | C16: BR-01 | D16: T-01 | E16: Weekend | F16: 2024-07-20 | G16: Active
A17: C-104 | B17: Kevin O'Connor | C17: BR-01 | D17: T-02 | E17: Night | F17: 2025-01-10 | G17: Under Review
A18: C-105 | B18: Sarah Jenkins | C18: BR-02 | D18: T-01 | E18: Morning | F18: 2023-08-14 | G18: Active
A19: C-106 | B19: David Kim | C19: BR-02 | D19: T-02 | E19: Evening | F19: 2024-05-18 | G19: Active
A20: C-107 | B20: Fatima Al-Sayed | C20: BR-02 | D20: T-03 | E20: Weekend | F20: 2024-09-01 | G20: Active
A21: C-108 | B21: Jason Miller | C21: BR-02 | D21: T-01 | E21: Night | F21: 2024-12-05 | G21: Under Review
A22: C-109 | B22: Chloe Dupont | C22: BR-03 | D22: T-01 | E22: Morning | F22: 2023-04-12 | G22: Active
A23: C-110 | B23: Ahmed Hassan | C23: BR-03 | D23: T-02 | E23: Evening | F23: 2024-02-28 | G23: Active
A24: C-111 | B24: Priya Patel | C24: BR-03 | D24: T-01 | E24: Weekend | F24: 2024-10-15 | G24: Active
... A28: C-115 | B28: Samantha Reed | C28: BR-04 | D28: T-01 | E28: Night | F28: 2025-01-22 | G28: Under Review

Sheet 03_Raw_POS_Journal
A1: RAW POS TRANSACTIONAL EVENT JOURNAL
A2: DATA INPUT: Paste raw POS export into Columns A:M (Navy #1F4E78) using Paste Special > Values. Columns N:O (Steel #2F5597) calculate automated latency and audit flags—do not overwrite.
A4: Event_ID | B4: Transaction_ID | C4: Event_Timestamp | D4: Branch_ID | E4: Terminal_ID | F4: Cashier_ID | G4: Supervisor_PIN | H4: Event_Type | I4: Tender_Type | J4: Item_Count | K4: Gross_Amount | L4: Net_Amount | M4: Order_Start_Time | N4: Latency_Seconds | O4: Audit_Flag
A5: EVT-10001 | B5: TX-80001 | C5: 46305.375 | D5: BR-01 | E5: T-02 | F5: C-101 | G5: NONE | H5: Sale Tender | I5: Cash | J5: 6 | K5: 55.61 | L5: 55.61 | M5: 46305.375 | N5: =IFERROR(IF(OR(ISBLANK(M5), M5="", ISBLANK(C5), C5=""), 0, MAX(0, ROUND((C5-M5)*86400, 0))), 0) | O5: =IF(H5="Post-Bill Void", IF(AND(G5="M-904", I5="Cash"), "EXCEPTION: Concurrent Cash Void", IF(AND(I5="Cash", N5>120), "CRITICAL: Delayed Cash Void", IF(N5>120, "EXCEPTION: Delayed Void", "Standard Void"))), IF(H5="Line Item Void", IF(I5="Cash", "EXCEPTION: Cash Line Void", "Standard Line Void"), IF(H5="No-Sale Drawer Opening", "DRAWER OPENING", "Standard Sale")))
A6: EVT-10002 | B6: TX-80002 | C6: 46305.382 | D6: BR-01 | E6: T-01 | F6: C-104 | G6: NONE | H6: Sale Tender | I6: Cash | J6: 5 | K6: 65.08 | L6: 65.08 | M6: 46305.382 | N6: =IFERROR(IF(OR(ISBLANK(M6), M6="", ISBLANK(C6), C6=""), 0, MAX(0, ROUND((C6-M6)*86400, 0))), 0) | O6: =IF(H6="Post-Bill Void", IF(AND(G6="M-904", I6="Cash"), "EXCEPTION: Concurrent Cash Void", IF(AND(I6="Cash", N6>120), "CRITICAL: Delayed Cash Void", IF(N6>120, "EXCEPTION: Delayed Void", "Standard Void"))), IF(H6="Line Item Void", IF(I6="Cash", "EXCEPTION: Cash Line Void", "Standard Line Void"), IF(H6="No-Sale Drawer Opening", "DRAWER OPENING", "Standard Sale")))
A7: EVT-10003 | B7: TX-80003 | C7: 46305.389 | D7: BR-02 | E7: T-01 | F7: C-108 | G7: NONE | H7: Sale Tender | I7: Card | J7: 1 | K7: 14.19 | L7: 14.19 | M7: 46305.389 | N7: =IFERROR(IF(OR(ISBLANK(M7), M7="", ISBLANK(C7), C7=""), 0, MAX(0, ROUND((C7-M7)*86400, 0))), 0) | O7: =IF(H7="Post-Bill Void", IF(AND(G7="M-904", I7="Cash"), "EXCEPTION: Concurrent Cash Void", IF(AND(I7="Cash", N7>120), "CRITICAL: Delayed Cash Void", IF(N7>120, "EXCEPTION: Delayed Void", "Standard Void"))), IF(H7="Line Item Void", IF(I7="Cash", "EXCEPTION: Cash Line Void", "Standard Line Void"), IF(H7="No-Sale Drawer Opening", "DRAWER OPENING", "Standard Sale")))
A8: EVT-10004 | B8: TX-80004 | C8: 46305.396 | D8: BR-04 | E8: T-01 | F8: C-114 | G8: NONE | H8: Sale Tender | I8: Delivery Aggregator | J8: 3 | K8: 27.8 | L8: 27.8 | M8: 46305.395 | N8: =IFERROR(IF(OR(ISBLANK(M8), M8="", ISBLANK(C8), C8=""), 0, MAX(0, ROUND((C8-M8)*86400, 0))), 0) | O8: =IF(H8="Post-Bill Void", IF(AND(G8="M-904", I8="Cash"), "EXCEPTION: Concurrent Cash Void", IF(AND(I8="Cash", N8>120), "CRITICAL: Delayed Cash Void", IF(N8>120, "EXCEPTION: Delayed Void", "Standard Void"))), IF(H8="Line Item Void", IF(I8="Cash", "EXCEPTION: Cash Line Void", "Standard Line Void"), IF(H8="No-Sale Drawer Opening", "DRAWER OPENING", "Standard Sale")))
A9: EVT-10005 | B9: TX-80005 | C9: 46305.403 | D9: BR-01 | E9: T-02 | F9: C-103 | G9: NONE | H9: Sale Tender | I9: Card | J9: 6 | K9: 71.67 | L9: 71.67 | M9: 46305.402 | N9: =IFERROR(IF(OR(ISBLANK(M9), M9="", ISBLANK(C9), C9=""), 0, MAX(0, ROUND((C9-M9)*86400, 0))), 0) | O9: =IF(H9="Post-Bill Void", IF(AND(G9="M-904", I9="Cash"), "EXCEPTION: Concurrent Cash Void", IF(AND(I9="Cash", N9>120), "CRITICAL: Delayed Cash Void", IF(N9>120, "EXCEPTION: Delayed Void", "Standard Void"))), IF(H9="Line Item Void", IF(I9="Cash", "EXCEPTION: Cash Line Void", "Standard Line Void"), IF(H9="No-Sale Drawer Opening", "DRAWER OPENING", "Standard Sale")))
A10: EVT-10006 | B10: TX-80006 | C10: 46305.41 | D10: BR-04 | E10: T-01 | F10: C-113 | G10: NONE | H10: Sale Tender | I10: Card | J10: 6 | K10: 54.13 | L10: 54.13 | M10: 46305.409 | N10: =IFERROR(IF(OR(ISBLANK(M10), M10="", ISBLANK(C10), C10=""), 0, MAX(0, ROUND((C10-M10)*86400, 0))), 0) | O10: =IF(H10="Post-Bill Void", IF(AND(G10="M-904", I10="Cash"), "EXCEPTION: Concurrent Cash Void", IF(AND(I10="Cash", N10>120), "CRITICAL: Delayed Cash Void", IF(N10>120, "EXCEPTION: Delayed Void", "Standard Void"))), IF(H10="Line Item Void", IF(I10="Cash", "EXCEPTION: Cash Line Void", "Standard Line Void"), IF(H10="No-Sale Drawer Opening", "DRAWER OPENING", "Standard Sale")))
A11: EVT-10007 | B11: TX-80007 | C11: 46305.417 | D11: BR-02 | E11: T-02 | F11: C-107 | G11: NONE | H11: Sale Tender | I11: Delivery Aggregator | J11: 4 | K11: 42.34 | L11: 42.34 | M11: 46305.417 | N11: =IFERROR(IF(OR(ISBLANK(M11), M11="", ISBLANK(C11), C11=""), 0, MAX(0, ROUND((C11-M11)*86400, 0))), 0) | O11: =IF(H11="Post-Bill Void", IF(AND(G11="M-904", I11="Cash"), "EXCEPTION: Concurrent Cash Void", IF(AND(I11="Cash", N11>120), "CRITICAL: Delayed Cash Void", IF(N11>120, "EXCEPTION: Delayed Void", "Standard Void"))), IF(H11="Line Item Void", IF(I11="Cash", "EXCEPTION: Cash Line Void", "Standard Line Void"), IF(H11="No-Sale Drawer Opening", "DRAWER OPENING", "Standard Sale")))
A12: EVT-10008 | B12: TX-80008 | C12: 46305.424 | D12: BR-03 | E12: T-01 | F12: C-110 | G12: NONE | H12: Sale Tender | I12: Card | J12: 6 | K12: 93.15 | L12: 93.15 | M12: 46305.423 | N12: =IFERROR(IF(OR(ISBLANK(M12), M12="", ISBLANK(C12), C12=""), 0, MAX(0, ROUND((C12-M12)*86400, 0))), 0) | O12: =IF(H12="Post-Bill Void", IF(AND(G12="M-904", I12="Cash"), "EXCEPTION: Concurrent Cash Void", IF(AND(I12="Cash", N12>120), "CRITICAL: Delayed Cash Void", IF(N12>120, "EXCEPTION: Delayed Void", "Standard Void"))), IF(H12="Line Item Void", IF(I12="Cash", "EXCEPTION: Cash Line Void", "Standard Line Void"), IF(H12="No-Sale Drawer Opening", "DRAWER OPENING", "Standard Sale")))
A13: EVT-10009 | B13: TX-80009 | C13: 46305.431 | D13: BR-01 | E13: T-01 | F13: C-102 | G13: NONE | H13: Sale Tender | I13: Cash | J13: 4 | K13: 42.1 | L13: 42.1 | M13: 46305.43 | N13: =IFERROR(IF(OR(ISBLANK(M13), M13="", ISBLANK(C13), C13=""), 0, MAX(0, ROUND((C13-M13)*86400, 0))), 0) | O13: =IF(H13="Post-Bill Void", IF(AND(G13="M-904", I13="Cash"), "EXCEPTION: Concurrent Cash Void", IF(AND(I13="Cash", N13>120), "CRITICAL: Delayed Cash Void", IF(N13>120, "EXCEPTION: Delayed Void", "Standard Void"))), IF(H13="Line Item Void", IF(I13="Cash", "EXCEPTION: Cash Line Void", "Standard Line Void"), IF(H13="No-Sale Drawer Opening", "DRAWER OPENING", "Standard Sale")))
A14: EVT-10010 | B14: TX-80010 | C14: 46305.438 | D14: BR-02 | E14: T-02 | F14: C-107 | G14: NONE | H14: Sale Tender | I14: Cash | J14: 1 | K14: 14.54 | L14: 14.54 | M14: 46305.438 | N14: =IFERROR(IF(OR(ISBLANK(M14), M14="", ISBLANK(C14), C14=""), 0, MAX(0, ROUND((C14-M14)*86400, 0))), 0) | O14: =IF(H14="Post-Bill Void", IF(AND(G14="M-904", I14="Cash"), "EXCEPTION: Concurrent Cash Void", IF(AND(I14="Cash", N14>120), "CRITICAL: Delayed Cash Void", IF(N14>120, "EXCEPTION: Delayed Void", "Standard Void"))), IF(H14="Line Item Void", IF(I14="Cash", "EXCEPTION: Cash Line Void", "Standard Line Void"), IF(H14="No-Sale Drawer Opening", "DRAWER OPENING", "Standard Sale")))
A15: EVT-10011 | B15: TX-80011 | C15: 46305.445 | D15: BR-03 | E15: T-01 | F15: C-109 | G15: NONE | H15: Sale Tender | I15: Cash | J15: 4 | K15: 45.87 | L15: 45.87 | M15: 46305.444 | N15: =IFERROR(IF(OR(ISBLANK(M15), M15="", ISBLANK(C15), C15=""), 0, MAX(0, ROUND((C15-M15)*86400, 0))), 0) | O15: =IF(H15="Post-Bill Void", IF(AND(G15="M-904", I15="Cash"), "EXCEPTION: Concurrent Cash Void", IF(AND(I15="Cash", N15>120), "CRITICAL: Delayed Cash Void", IF(N15>120, "EXCEPTION: Delayed Void", "Standard Void"))), IF(H15="Line Item Void", IF(I15="Cash", "EXCEPTION: Cash Line Void", "Standard Line Void"), IF(H15="No-Sale Drawer Opening", "DRAWER OPENING", "Standard Sale")))
A16: EVT-10012 | B16: TX-80012 | C16: 46305.452 | D16: BR-04 | E16: T-01 | F16: C-113 | G16: NONE | H16: Sale Tender | I16: Card | J16: 5 | K16: 52.35 | L16: 52.35 | M16: 46305.451 | N16: =IFERROR(IF(OR(ISBLANK(M16), M16="", ISBLANK(C16), C16=""), 0, MAX(0, ROUND((C16-M16)*86400, 0))), 0) | O16: =IF(H16="Post-Bill Void", IF(AND(G16="M-904", I16="Cash"), "EXCEPTION: Concurrent Cash Void", IF(AND(I16="Cash", N16>120), "CRITICAL: Delayed Cash Void", IF(N16>120, "EXCEPTION: Delayed Void", "Standard Void"))), IF(H16="Line Item Void", IF(I16="Cash", "EXCEPTION: Cash Line Void", "Standard Line Void"), IF(H16="No-Sale Drawer Opening", "DRAWER OPENING", "Standard Sale")))
... A678: EVT-10581 | B678: TX-80581 | C678: 46312.265 | D678: BR-02 | E678: T-01 | F678: C-108 | G678: M-902 | H678: Line Item Void | I678: Cash | J678: 2 | K678: 38.2 | L678: 0 | M678: 46312.265 | N678: =IFERROR(IF(OR(ISBLANK(M678), M678="", ISBLANK(C678), C678=""), 0, MAX(0, ROUND((C678-M678)*86400, 0))), 0) | O678: =IF(H678="Post-Bill Void", IF(AND(G678="M-904", I678="Cash"), "EXCEPTION: Concurrent Cash Void", IF(AND(I678="Cash", N678>120), "CRITICAL: Delayed Cash Void", IF(N678>120, "EXCEPTION: Delayed Void", "Standard Void"))), IF(H678="Line Item Void", IF(I678="Cash", "EXCEPTION: Cash Line Void", "Standard Line Void"), IF(H678="No-Sale Drawer Opening", "DRAWER OPENING", "Standard Sale")))

Sheet 04_Engine_Voids
A1: AUDIT ENGINE 1: POST-SETTLEMENT CASH VOID ANALYSIS
A2: AUTOMATED CALCULATION: Evaluates post-settlement void frequency, cash concentration, and elapsed latency between order initiation and cancellation. Steel headers (#2F5597) update dynamically.
A4: Cashier ID | B4: Cashier Name | C4: Branch | D4: Total Sales Count | E4: Cash Sales Count | F4: Total Voids | G4: Cash Voids | H4: Cash Void Rate % | I4: Avg Void Latency (s) | J4: Delayed Voids (>120s) | K4: Critical Cash Voids (>120s) | L4: Void Exposure ($) | M4: Cash Void Z-Score | N4: Void Risk Classification
A5: C-101 | B5: =IFERROR(VLOOKUP(A5, '02_Cashier_Register'!$A$14:$G$28, 2, FALSE), "Unknown") | C5: =IFERROR(VLOOKUP(A5, '02_Cashier_Register'!$A$14:$G$28, 3, FALSE), "Unknown") | D5: =COUNTIFS('03_Raw_POS_Journal'!$F$5:$F$678, A5, '03_Raw_POS_Journal'!$H$5:$H$678, "Sale Tender") | E5: =COUNTIFS('03_Raw_POS_Journal'!$F$5:$F$678, A5, '03_Raw_POS_Journal'!$H$5:$H$678, "Sale Tender", '03_Raw_POS_Journal'!$I$5:$I$678, "Cash") | F5: =COUNTIFS('03_Raw_POS_Journal'!$F$5:$F$678, A5, '03_Raw_POS_Journal'!$H$5:$H$678, "Post-Bill Void") | G5: =COUNTIFS('03_Raw_POS_Journal'!$F$5:$F$678, A5, '03_Raw_POS_Journal'!$H$5:$H$678, "Post-Bill Void", '03_Raw_POS_Journal'!$I$5:$I$678, "Cash") | H5: =IFERROR(IF(E5>0, G5/E5, 0), 0) | I5: =IFERROR(AVERAGEIFS('03_Raw_POS_Journal'!$N$5:$N$678, '03_Raw_POS_Journal'!$F$5:$F$678, A5, '03_Raw_POS_Journal'!$H$5:$H$678, "Post-Bill Void"), 0) | J5: =COUNTIFS('03_Raw_POS_Journal'!$F$5:$F$678, A5, '03_Raw_POS_Journal'!$H$5:$H$678, "Post-Bill Void", '03_Raw_POS_Journal'!$N$5:$N$678, ">120") | K5: =COUNTIFS('03_Raw_POS_Journal'!$F$5:$F$678, A5, '03_Raw_POS_Journal'!$H$5:$H$678, "Post-Bill Void", '03_Raw_POS_Journal'!$I$5:$I$678, "Cash", '03_Raw_POS_Journal'!$N$5:$N$678, ">120") | L5: =SUMIFS('03_Raw_POS_Journal'!$K$5:$K$678, '03_Raw_POS_Journal'!$F$5:$F$678, A5, '03_Raw_POS_Journal'!$H$5:$H$678, "Post-Bill Void", '03_Raw_POS_Journal'!$I$5:$I$678, "Cash") | M5: =IFERROR(IF(_xlfn.STDEV.S($H$5:$H$19)=0, 0, (H5 - AVERAGE($H$5:$H$19)) / _xlfn.STDEV.S($H$5:$H$19)), 0) | N5: =IF(K5>=5, "CRITICAL RISK", IF(OR(K5>=2, M5>=1.5, G5>=5), "ELEVATED RISK", "STANDARD"))
A6: C-102 | B6: =IFERROR(VLOOKUP(A6, '02_Cashier_Register'!$A$14:$G$28, 2, FALSE), "Unknown") | C6: =IFERROR(VLOOKUP(A6, '02_Cashier_Register'!$A$14:$G$28, 3, FALSE), "Unknown") | D6: =COUNTIFS('03_Raw_POS_Journal'!$F$5:$F$678, A6, '03_Raw_POS_Journal'!$H$5:$H$678, "Sale Tender") | E6: =COUNTIFS('03_Raw_POS_Journal'!$F$5:$F$678, A6, '03_Raw_POS_Journal'!$H$5:$H$678, "Sale Tender", '03_Raw_POS_Journal'!$I$5:$I$678, "Cash") | F6: =COUNTIFS('03_Raw_POS_Journal'!$F$5:$F$678, A6, '03_Raw_POS_Journal'!$H$5:$H$678, "Post-Bill Void") | G6: =COUNTIFS('03_Raw_POS_Journal'!$F$5:$F$678, A6, '03_Raw_POS_Journal'!$H$5:$H$678, "Post-Bill Void", '03_Raw_POS_Journal'!$I$5:$I$678, "Cash") | H6: =IFERROR(IF(E6>0, G6/E6, 0), 0) | I6: =IFERROR(AVERAGEIFS('03_Raw_POS_Journal'!$N$5:$N$678, '03_Raw_POS_Journal'!$F$5:$F$678, A6, '03_Raw_POS_Journal'!$H$5:$H$678, "Post-Bill Void"), 0) | J6: =COUNTIFS('03_Raw_POS_Journal'!$F$5:$F$678, A6, '03_Raw_POS_Journal'!$H$5:$H$678, "Post-Bill Void", '03_Raw_POS_Journal'!$N$5:$N$678, ">120") | K6: =COUNTIFS('03_Raw_POS_Journal'!$F$5:$F$678, A6, '03_Raw_POS_Journal'!$H$5:$H$678, "Post-Bill Void", '03_Raw_POS_Journal'!$I$5:$I$678, "Cash", '03_Raw_POS_Journal'!$N$5:$N$678, ">120") | L6: =SUMIFS('03_Raw_POS_Journal'!$K$5:$K$678, '03_Raw_POS_Journal'!$F$5:$F$678, A6, '03_Raw_POS_Journal'!$H$5:$H$678, "Post-Bill Void", '03_Raw_POS_Journal'!$I$5:$I$678, "Cash") | M6: =IFERROR(IF(_xlfn.STDEV.S($H$5:$H$19)=0, 0, (H6 - AVERAGE($H$5:$H$19)) / _xlfn.STDEV.S($H$5:$H$19)), 0) | N6: =IF(K6>=5, "CRITICAL RISK", IF(OR(K6>=2, M6>=1.5, G6>=5), "ELEVATED RISK", "STANDARD"))
A7: C-103 | B7: =IFERROR(VLOOKUP(A7, '02_Cashier_Register'!$A$14:$G$28, 2, FALSE), "Unknown") | C7: =IFERROR(VLOOKUP(A7, '02_Cashier_Register'!$A$14:$G$28, 3, FALSE), "Unknown") | D7: =COUNTIFS('03_Raw_POS_Journal'!$F$5:$F$678, A7, '03_Raw_POS_Journal'!$H$5:$H$678, "Sale Tender") | E7: =COUNTIFS('03_Raw_POS_Journal'!$F$5:$F$678, A7, '03_Raw_POS_Journal'!$H$5:$H$678, "Sale Tender", '03_Raw_POS_Journal'!$I$5:$I$678, "Cash") | F7: =COUNTIFS('03_Raw_POS_Journal'!$F$5:$F$678, A7, '03_Raw_POS_Journal'!$H$5:$H$678, "Post-Bill Void") | G7: =COUNTIFS('03_Raw_POS_Journal'!$F$5:$F$678, A7, '03_Raw_POS_Journal'!$H$5:$H$678, "Post-Bill Void", '03_Raw_POS_Journal'!$I$5:$I$678, "Cash") | H7: =IFERROR(IF(E7>0, G7/E7, 0), 0) | I7: =IFERROR(AVERAGEIFS('03_Raw_POS_Journal'!$N$5:$N$678, '03_Raw_POS_Journal'!$F$5:$F$678, A7, '03_Raw_POS_Journal'!$H$5:$H$678, "Post-Bill Void"), 0) | J7: =COUNTIFS('03_Raw_POS_Journal'!$F$5:$F$678, A7, '03_Raw_POS_Journal'!$H$5:$H$678, "Post-Bill Void", '03_Raw_POS_Journal'!$N$5:$N$678, ">120") | K7: =COUNTIFS('03_Raw_POS_Journal'!$F$5:$F$678, A7, '03_Raw_POS_Journal'!$H$5:$H$678, "Post-Bill Void", '03_Raw_POS_Journal'!$I$5:$I$678, "Cash", '03_Raw_POS_Journal'!$N$5:$N$678, ">120") | L7: =SUMIFS('03_Raw_POS_Journal'!$K$5:$K$678, '03_Raw_POS_Journal'!$F$5:$F$678, A7, '03_Raw_POS_Journal'!$H$5:$H$678, "Post-Bill Void", '03_Raw_POS_Journal'!$I$5:$I$678, "Cash") | M7: =IFERROR(IF(_xlfn.STDEV.S($H$5:$H$19)=0, 0, (H7 - AVERAGE($H$5:$H$19)) / _xlfn.STDEV.S($H$5:$H$19)), 0) | N7: =IF(K7>=5, "CRITICAL RISK", IF(OR(K7>=2, M7>=1.5, G7>=5), "ELEVATED RISK", "STANDARD"))
A8: C-104 | B8: =IFERROR(VLOOKUP(A8, '02_Cashier_Register'!$A$14:$G$28, 2, FALSE), "Unknown") | C8: =IFERROR(VLOOKUP(A8, '02_Cashier_Register'!$A$14:$G$28, 3, FALSE), "Unknown") | D8: =COUNTIFS('03_Raw_POS_Journal'!$F$5:$F$678, A8, '03_Raw_POS_Journal'!$H$5:$H$678, "Sale Tender") | E8: =COUNTIFS('03_Raw_POS_Journal'!$F$5:$F$678, A8, '03_Raw_POS_Journal'!$H$5:$H$678, "Sale Tender", '03_Raw_POS_Journal'!$I$5:$I$678, "Cash") | F8: =COUNTIFS('03_Raw_POS_Journal'!$F$5:$F$678, A8, '03_Raw_POS_Journal'!$H$5:$H$678, "Post-Bill Void") | G8: =COUNTIFS('03_Raw_POS_Journal'!$F$5:$F$678, A8, '03_Raw_POS_Journal'!$H$5:$H$678, "Post-Bill Void", '03_Raw_POS_Journal'!$I$5:$I$678, "Cash") | H8: =IFERROR(IF(E8>0, G8/E8, 0), 0) | I8: =IFERROR(AVERAGEIFS('03_Raw_POS_Journal'!$N$5:$N$678, '03_Raw_POS_Journal'!$F$5:$F$678, A8, '03_Raw_POS_Journal'!$H$5:$H$678, "Post-Bill Void"), 0) | J8: =COUNTIFS('03_Raw_POS_Journal'!$F$5:$F$678, A8, '03_Raw_POS_Journal'!$H$5:$H$678, "Post-Bill Void", '03_Raw_POS_Journal'!$N$5:$N$678, ">120") | K8: =COUNTIFS('03_Raw_POS_Journal'!$F$5:$F$678, A8, '03_Raw_POS_Journal'!$H$5:$H$678, "Post-Bill Void", '03_Raw_POS_Journal'!$I$5:$I$678, "Cash", '03_Raw_POS_Journal'!$N$5:$N$678, ">120") | L8: =SUMIFS('03_Raw_POS_Journal'!$K$5:$K$678, '03_Raw_POS_Journal'!$F$5:$F$678, A8, '03_Raw_POS_Journal'!$H$5:$H$678, "Post-Bill Void", '03_Raw_POS_Journal'!$I$5:$I$678, "Cash") | M8: =IFERROR(IF(_xlfn.STDEV.S($H$5:$H$19)=0, 0, (H8 - AVERAGE($H$5:$H$19)) / _xlfn.STDEV.S($H$5:$H$19)), 0) | N8: =IF(K8>=5, "CRITICAL RISK", IF(OR(K8>=2, M8>=1.5, G8>=5), "ELEVATED RISK", "STANDARD"))
A9: C-105 | B9: =IFERROR(VLOOKUP(A9, '02_Cashier_Register'!$A$14:$G$28, 2, FALSE), "Unknown") | C9: =IFERROR(VLOOKUP(A9, '02_Cashier_Register'!$A$14:$G$28, 3, FALSE), "Unknown") | D9: =COUNTIFS('03_Raw_POS_Journal'!$F$5:$F$678, A9, '03_Raw_POS_Journal'!$H$5:$H$678, "Sale Tender") | E9: =COUNTIFS('03_Raw_POS_Journal'!$F$5:$F$678, A9, '03_Raw_POS_Journal'!$H$5:$H$678, "Sale Tender", '03_Raw_POS_Journal'!$I$5:$I$678, "Cash") | F9: =COUNTIFS('03_Raw_POS_Journal'!$F$5:$F$678, A9, '03_Raw_POS_Journal'!$H$5:$H$678, "Post-Bill Void") | G9: =COUNTIFS('03_Raw_POS_Journal'!$F$5:$F$678, A9, '03_Raw_POS_Journal'!$H$5:$H$678, "Post-Bill Void", '03_Raw_POS_Journal'!$I$5:$I$678, "Cash") | H9: =IFERROR(IF(E9>0, G9/E9, 0), 0) | I9: =IFERROR(AVERAGEIFS('03_Raw_POS_Journal'!$N$5:$N$678, '03_Raw_POS_Journal'!$F$5:$F$678, A9, '03_Raw_POS_Journal'!$H$5:$H$678, "Post-Bill Void"), 0) | J9: =COUNTIFS('03_Raw_POS_Journal'!$F$5:$F$678, A9, '03_Raw_POS_Journal'!$H$5:$H$678, "Post-Bill Void", '03_Raw_POS_Journal'!$N$5:$N$678, ">120") | K9: =COUNTIFS('03_Raw_POS_Journal'!$F$5:$F$678, A9, '03_Raw_POS_Journal'!$H$5:$H$678, "Post-Bill Void", '03_Raw_POS_Journal'!$I$5:$I$678, "Cash", '03_Raw_POS_Journal'!$N$5:$N$678, ">120") | L9: =SUMIFS('03_Raw_POS_Journal'!$K$5:$K$678, '03_Raw_POS_Journal'!$F$5:$F$678, A9, '03_Raw_POS_Journal'!$H$5:$H$678, "Post-Bill Void", '03_Raw_POS_Journal'!$I$5:$I$678, "Cash") | M9: =IFERROR(IF(_xlfn.STDEV.S($H$5:$H$19)=0, 0, (H9 - AVERAGE($H$5:$H$19)) / _xlfn.STDEV.S($H$5:$H$19)), 0) | N9: =IF(K9>=5, "CRITICAL RISK", IF(OR(K9>=2, M9>=1.5, G9>=5), "ELEVATED RISK", "STANDARD"))
A10: C-106 | B10: =IFERROR(VLOOKUP(A10, '02_Cashier_Register'!$A$14:$G$28, 2, FALSE), "Unknown") | C10: =IFERROR(VLOOKUP(A10, '02_Cashier_Register'!$A$14:$G$28, 3, FALSE), "Unknown") | D10: =COUNTIFS('03_Raw_POS_Journal'!$F$5:$F$678, A10, '03_Raw_POS_Journal'!$H$5:$H$678, "Sale Tender") | E10: =COUNTIFS('03_Raw_POS_Journal'!$F$5:$F$678, A10, '03_Raw_POS_Journal'!$H$5:$H$678, "Sale Tender", '03_Raw_POS_Journal'!$I$5:$I$678, "Cash") | F10: =COUNTIFS('03_Raw_POS_Journal'!$F$5:$F$678, A10, '03_Raw_POS_Journal'!$H$5:$H$678, "Post-Bill Void") | G10: =COUNTIFS('03_Raw_POS_Journal'!$F$5:$F$678, A10, '03_Raw_POS_Journal'!$H$5:$H$678, "Post-Bill Void", '03_Raw_POS_Journal'!$I$5:$I$678, "Cash") | H10: =IFERROR(IF(E10>0, G10/E10, 0), 0) | I10: =IFERROR(AVERAGEIFS('03_Raw_POS_Journal'!$N$5:$N$678, '03_Raw_POS_Journal'!$F$5:$F$678, A10, '03_Raw_POS_Journal'!$H$5:$H$678, "Post-Bill Void"), 0) | J10: =COUNTIFS('03_Raw_POS_Journal'!$F$5:$F$678, A10, '03_Raw_POS_Journal'!$H$5:$H$678, "Post-Bill Void", '03_Raw_POS_Journal'!$N$5:$N$678, ">120") | K10: =COUNTIFS('03_Raw_POS_Journal'!$F$5:$F$678, A10, '03_Raw_POS_Journal'!$H$5:$H$678, "Post-Bill Void", '03_Raw_POS_Journal'!$I$5:$I$678, "Cash", '03_Raw_POS_Journal'!$N$5:$N$678, ">120") | L10: =SUMIFS('03_Raw_POS_Journal'!$K$5:$K$678, '03_Raw_POS_Journal'!$F$5:$F$678, A10, '03_Raw_POS_Journal'!$H$5:$H$678, "Post-Bill Void", '03_Raw_POS_Journal'!$I$5:$I$678, "Cash") | M10: =IFERROR(IF(_xlfn.STDEV.S($H$5:$H$19)=0, 0, (H10 - AVERAGE($H$5:$H$19)) / _xlfn.STDEV.S($H$5:$H$19)), 0) | N10: =IF(K10>=5, "CRITICAL RISK", IF(OR(K10>=2, M10>=1.5, G10>=5), "ELEVATED RISK", "STANDARD"))
A11: C-107 | B11: =IFERROR(VLOOKUP(A11, '02_Cashier_Register'!$A$14:$G$28, 2, FALSE), "Unknown") | C11: =IFERROR(VLOOKUP(A11, '02_Cashier_Register'!$A$14:$G$28, 3, FALSE), "Unknown") | D11: =COUNTIFS('03_Raw_POS_Journal'!$F$5:$F$678, A11, '03_Raw_POS_Journal'!$H$5:$H$678, "Sale Tender") | E11: =COUNTIFS('03_Raw_POS_Journal'!$F$5:$F$678, A11, '03_Raw_POS_Journal'!$H$5:$H$678, "Sale Tender", '03_Raw_POS_Journal'!$I$5:$I$678, "Cash") | F11: =COUNTIFS('03_Raw_POS_Journal'!$F$5:$F$678, A11, '03_Raw_POS_Journal'!$H$5:$H$678, "Post-Bill Void") | G11: =COUNTIFS('03_Raw_POS_Journal'!$F$5:$F$678, A11, '03_Raw_POS_Journal'!$H$5:$H$678, "Post-Bill Void", '03_Raw_POS_Journal'!$I$5:$I$678, "Cash") | H11: =IFERROR(IF(E11>0, G11/E11, 0), 0) | I11: =IFERROR(AVERAGEIFS('03_Raw_POS_Journal'!$N$5:$N$678, '03_Raw_POS_Journal'!$F$5:$F$678, A11, '03_Raw_POS_Journal'!$H$5:$H$678, "Post-Bill Void"), 0) | J11: =COUNTIFS('03_Raw_POS_Journal'!$F$5:$F$678, A11, '03_Raw_POS_Journal'!$H$5:$H$678, "Post-Bill Void", '03_Raw_POS_Journal'!$N$5:$N$678, ">120") | K11: =COUNTIFS('03_Raw_POS_Journal'!$F$5:$F$678, A11, '03_Raw_POS_Journal'!$H$5:$H$678, "Post-Bill Void", '03_Raw_POS_Journal'!$I$5:$I$678, "Cash", '03_Raw_POS_Journal'!$N$5:$N$678, ">120") | L11: =SUMIFS('03_Raw_POS_Journal'!$K$5:$K$678, '03_Raw_POS_Journal'!$F$5:$F$678, A11, '03_Raw_POS_Journal'!$H$5:$H$678, "Post-Bill Void", '03_Raw_POS_Journal'!$I$5:$I$678, "Cash") | M11: =IFERROR(IF(_xlfn.STDEV.S($H$5:$H$19)=0, 0, (H11 - AVERAGE($H$5:$H$19)) / _xlfn.STDEV.S($H$5:$H$19)), 0) | N11: =IF(K11>=5, "CRITICAL RISK", IF(OR(K11>=2, M11>=1.5, G11>=5), "ELEVATED RISK", "STANDARD"))
A12: C-108 | B12: =IFERROR(VLOOKUP(A12, '02_Cashier_Register'!$A$14:$G$28, 2, FALSE), "Unknown") | C12: =IFERROR(VLOOKUP(A12, '02_Cashier_Register'!$A$14:$G$28, 3, FALSE), "Unknown") | D12: =COUNTIFS('03_Raw_POS_Journal'!$F$5:$F$678, A12, '03_Raw_POS_Journal'!$H$5:$H$678, "Sale Tender") | E12: =COUNTIFS('03_Raw_POS_Journal'!$F$5:$F$678, A12, '03_Raw_POS_Journal'!$H$5:$H$678, "Sale Tender", '03_Raw_POS_Journal'!$I$5:$I$678, "Cash") | F12: =COUNTIFS('03_Raw_POS_Journal'!$F$5:$F$678, A12, '03_Raw_POS_Journal'!$H$5:$H$678, "Post-Bill Void") | G12: =COUNTIFS('03_Raw_POS_Journal'!$F$5:$F$678, A12, '03_Raw_POS_Journal'!$H$5:$H$678, "Post-Bill Void", '03_Raw_POS_Journal'!$I$5:$I$678, "Cash") | H12: =IFERROR(IF(E12>0, G12/E12, 0), 0) | I12: =IFERROR(AVERAGEIFS('03_Raw_POS_Journal'!$N$5:$N$678, '03_Raw_POS_Journal'!$F$5:$F$678, A12, '03_Raw_POS_Journal'!$H$5:$H$678, "Post-Bill Void"), 0) | J12: =COUNTIFS('03_Raw_POS_Journal'!$F$5:$F$678, A12, '03_Raw_POS_Journal'!$H$5:$H$678, "Post-Bill Void", '03_Raw_POS_Journal'!$N$5:$N$678, ">120") | K12: =COUNTIFS('03_Raw_POS_Journal'!$F$5:$F$678, A12, '03_Raw_POS_Journal'!$H$5:$H$678, "Post-Bill Void", '03_Raw_POS_Journal'!$I$5:$I$678, "Cash", '03_Raw_POS_Journal'!$N$5:$N$678, ">120") | L12: =SUMIFS('03_Raw_POS_Journal'!$K$5:$K$678, '03_Raw_POS_Journal'!$F$5:$F$678, A12, '03_Raw_POS_Journal'!$H$5:$H$678, "Post-Bill Void", '03_Raw_POS_Journal'!$I$5:$I$678, "Cash") | M12: =IFERROR(IF(_xlfn.STDEV.S($H$5:$H$19)=0, 0, (H12 - AVERAGE($H$5:$H$19)) / _xlfn.STDEV.S($H$5:$H$19)), 0) | N12: =IF(K12>=5, "CRITICAL RISK", IF(OR(K12>=2, M12>=1.5, G12>=5), "ELEVATED RISK", "STANDARD"))
A13: C-109 | B13: =IFERROR(VLOOKUP(A13, '02_Cashier_Register'!$A$14:$G$28, 2, FALSE), "Unknown") | C13: =IFERROR(VLOOKUP(A13, '02_Cashier_Register'!$A$14:$G$28, 3, FALSE), "Unknown") | D13: =COUNTIFS('03_Raw_POS_Journal'!$F$5:$F$678, A13, '03_Raw_POS_Journal'!$H$5:$H$678, "Sale Tender") | E13: =COUNTIFS('03_Raw_POS_Journal'!$F$5:$F$678, A13, '03_Raw_POS_Journal'!$H$5:$H$678, "Sale Tender", '03_Raw_POS_Journal'!$I$5:$I$678, "Cash") | F13: =COUNTIFS('03_Raw_POS_Journal'!$F$5:$F$678, A13, '03_Raw_POS_Journal'!$H$5:$H$678, "Post-Bill Void") | G13: =COUNTIFS('03_Raw_POS_Journal'!$F$5:$F$678, A13, '03_Raw_POS_Journal'!$H$5:$H$678, "Post-Bill Void", '03_Raw_POS_Journal'!$I$5:$I$678, "Cash") | H13: =IFERROR(IF(E13>0, G13/E13, 0), 0) | I13: =IFERROR(AVERAGEIFS('03_Raw_POS_Journal'!$N$5:$N$678, '03_Raw_POS_Journal'!$F$5:$F$678, A13, '03_Raw_POS_Journal'!$H$5:$H$678, "Post-Bill Void"), 0) | J13: =COUNTIFS('03_Raw_POS_Journal'!$F$5:$F$678, A13, '03_Raw_POS_Journal'!$H$5:$H$678, "Post-Bill Void", '03_Raw_POS_Journal'!$N$5:$N$678, ">120") | K13: =COUNTIFS('03_Raw_POS_Journal'!$F$5:$F$678, A13, '03_Raw_POS_Journal'!$H$5:$H$678, "Post-Bill Void", '03_Raw_POS_Journal'!$I$5:$I$678, "Cash", '03_Raw_POS_Journal'!$N$5:$N$678, ">120") | L13: =SUMIFS('03_Raw_POS_Journal'!$K$5:$K$678, '03_Raw_POS_Journal'!$F$5:$F$678, A13, '03_Raw_POS_Journal'!$H$5:$H$678, "Post-Bill Void", '03_Raw_POS_Journal'!$I$5:$I$678, "Cash") | M13: =IFERROR(IF(_xlfn.STDEV.S($H$5:$H$19)=0, 0, (H13 - AVERAGE($H$5:$H$19)) / _xlfn.STDEV.S($H$5:$H$19)), 0) | N13: =IF(K13>=5, "CRITICAL RISK", IF(OR(K13>=2, M13>=1.5, G13>=5), "ELEVATED RISK", "STANDARD"))
A14: C-110 | B14: =IFERROR(VLOOKUP(A14, '02_Cashier_Register'!$A$14:$G$28, 2, FALSE), "Unknown") | C14: =IFERROR(VLOOKUP(A14, '02_Cashier_Register'!$A$14:$G$28, 3, FALSE), "Unknown") | D14: =COUNTIFS('03_Raw_POS_Journal'!$F$5:$F$678, A14, '03_Raw_POS_Journal'!$H$5:$H$678, "Sale Tender") | E14: =COUNTIFS('03_Raw_POS_Journal'!$F$5:$F$678, A14, '03_Raw_POS_Journal'!$H$5:$H$678, "Sale Tender", '03_Raw_POS_Journal'!$I$5:$I$678, "Cash") | F14: =COUNTIFS('03_Raw_POS_Journal'!$F$5:$F$678, A14, '03_Raw_POS_Journal'!$H$5:$H$678, "Post-Bill Void") | G14: =COUNTIFS('03_Raw_POS_Journal'!$F$5:$F$678, A14, '03_Raw_POS_Journal'!$H$5:$H$678, "Post-Bill Void", '03_Raw_POS_Journal'!$I$5:$I$678, "Cash") | H14: =IFERROR(IF(E14>0, G14/E14, 0), 0) | I14: =IFERROR(AVERAGEIFS('03_Raw_POS_Journal'!$N$5:$N$678, '03_Raw_POS_Journal'!$F$5:$F$678, A14, '03_Raw_POS_Journal'!$H$5:$H$678, "Post-Bill Void"), 0) | J14: =COUNTIFS('03_Raw_POS_Journal'!$F$5:$F$678, A14, '03_Raw_POS_Journal'!$H$5:$H$678, "Post-Bill Void", '03_Raw_POS_Journal'!$N$5:$N$678, ">120") | K14: =COUNTIFS('03_Raw_POS_Journal'!$F$5:$F$678, A14, '03_Raw_POS_Journal'!$H$5:$H$678, "Post-Bill Void", '03_Raw_POS_Journal'!$I$5:$I$678, "Cash", '03_Raw_POS_Journal'!$N$5:$N$678, ">120") | L14: =SUMIFS('03_Raw_POS_Journal'!$K$5:$K$678, '03_Raw_POS_Journal'!$F$5:$F$678, A14, '03_Raw_POS_Journal'!$H$5:$H$678, "Post-Bill Void", '03_Raw_POS_Journal'!$I$5:$I$678, "Cash") | M14: =IFERROR(IF(_xlfn.STDEV.S($H$5:$H$19)=0, 0, (H14 - AVERAGE($H$5:$H$19)) / _xlfn.STDEV.S($H$5:$H$19)), 0) | N14: =IF(K14>=5, "CRITICAL RISK", IF(OR(K14>=2, M14>=1.5, G14>=5), "ELEVATED RISK", "STANDARD"))
A15: C-111 | B15: =IFERROR(VLOOKUP(A15, '02_Cashier_Register'!$A$14:$G$28, 2, FALSE), "Unknown") | C15: =IFERROR(VLOOKUP(A15, '02_Cashier_Register'!$A$14:$G$28, 3, FALSE), "Unknown") | D15: =COUNTIFS('03_Raw_POS_Journal'!$F$5:$F$678, A15, '03_Raw_POS_Journal'!$H$5:$H$678, "Sale Tender") | E15: =COUNTIFS('03_Raw_POS_Journal'!$F$5:$F$678, A15, '03_Raw_POS_Journal'!$H$5:$H$678, "Sale Tender", '03_Raw_POS_Journal'!$I$5:$I$678, "Cash") | F15: =COUNTIFS('03_Raw_POS_Journal'!$F$5:$F$678, A15, '03_Raw_POS_Journal'!$H$5:$H$678, "Post-Bill Void") | G15: =COUNTIFS('03_Raw_POS_Journal'!$F$5:$F$678, A15, '03_Raw_POS_Journal'!$H$5:$H$678, "Post-Bill Void", '03_Raw_POS_Journal'!$I$5:$I$678, "Cash") | H15: =IFERROR(IF(E15>0, G15/E15, 0), 0) | I15: =IFERROR(AVERAGEIFS('03_Raw_POS_Journal'!$N$5:$N$678, '03_Raw_POS_Journal'!$F$5:$F$678, A15, '03_Raw_POS_Journal'!$H$5:$H$678, "Post-Bill Void"), 0) | J15: =COUNTIFS('03_Raw_POS_Journal'!$F$5:$F$678, A15, '03_Raw_POS_Journal'!$H$5:$H$678, "Post-Bill Void", '03_Raw_POS_Journal'!$N$5:$N$678, ">120") | K15: =COUNTIFS('03_Raw_POS_Journal'!$F$5:$F$678, A15, '03_Raw_POS_Journal'!$H$5:$H$678, "Post-Bill Void", '03_Raw_POS_Journal'!$I$5:$I$678, "Cash", '03_Raw_POS_Journal'!$N$5:$N$678, ">120") | L15: =SUMIFS('03_Raw_POS_Journal'!$K$5:$K$678, '03_Raw_POS_Journal'!$F$5:$F$678, A15, '03_Raw_POS_Journal'!$H$5:$H$678, "Post-Bill Void", '03_Raw_POS_Journal'!$I$5:$I$678, "Cash") | M15: =IFERROR(IF(_xlfn.STDEV.S($H$5:$H$19)=0, 0, (H15 - AVERAGE($H$5:$H$19)) / _xlfn.STDEV.S($H$5:$H$19)), 0) | N15: =IF(K15>=5, "CRITICAL RISK", IF(OR(K15>=2, M15>=1.5, G15>=5), "ELEVATED RISK", "STANDARD"))
A16: C-112 | B16: =IFERROR(VLOOKUP(A16, '02_Cashier_Register'!$A$14:$G$28, 2, FALSE), "Unknown") | C16: =IFERROR(VLOOKUP(A16, '02_Cashier_Register'!$A$14:$G$28, 3, FALSE), "Unknown") | D16: =COUNTIFS('03_Raw_POS_Journal'!$F$5:$F$678, A16, '03_Raw_POS_Journal'!$H$5:$H$678, "Sale Tender") | E16: =COUNTIFS('03_Raw_POS_Journal'!$F$5:$F$678, A16, '03_Raw_POS_Journal'!$H$5:$H$678, "Sale Tender", '03_Raw_POS_Journal'!$I$5:$I$678, "Cash") | F16: =COUNTIFS('03_Raw_POS_Journal'!$F$5:$F$678, A16, '03_Raw_POS_Journal'!$H$5:$H$678, "Post-Bill Void") | G16: =COUNTIFS('03_Raw_POS_Journal'!$F$5:$F$678, A16, '03_Raw_POS_Journal'!$H$5:$H$678, "Post-Bill Void", '03_Raw_POS_Journal'!$I$5:$I$678, "Cash") | H16: =IFERROR(IF(E16>0, G16/E16, 0), 0) | I16: =IFERROR(AVERAGEIFS('03_Raw_POS_Journal'!$N$5:$N$678, '03_Raw_POS_Journal'!$F$5:$F$678, A16, '03_Raw_POS_Journal'!$H$5:$H$678, "Post-Bill Void"), 0) | J16: =COUNTIFS('03_Raw_POS_Journal'!$F$5:$F$678, A16, '03_Raw_POS_Journal'!$H$5:$H$678, "Post-Bill Void", '03_Raw_POS_Journal'!$N$5:$N$678, ">120") | K16: =COUNTIFS('03_Raw_POS_Journal'!$F$5:$F$678, A16, '03_Raw_POS_Journal'!$H$5:$H$678, "Post-Bill Void", '03_Raw_POS_Journal'!$I$5:$I$678, "Cash", '03_Raw_POS_Journal'!$N$5:$N$678, ">120") | L16: =SUMIFS('03_Raw_POS_Journal'!$K$5:$K$678, '03_Raw_POS_Journal'!$F$5:$F$678, A16, '03_Raw_POS_Journal'!$H$5:$H$678, "Post-Bill Void", '03_Raw_POS_Journal'!$I$5:$I$678, "Cash") | M16: =IFERROR(IF(_xlfn.STDEV.S($H$5:$H$19)=0, 0, (H16 - AVERAGE($H$5:$H$19)) / _xlfn.STDEV.S($H$5:$H$19)), 0) | N16: =IF(K16>=5, "CRITICAL RISK", IF(OR(K16>=2, M16>=1.5, G16>=5), "ELEVATED RISK", "STANDARD"))
... A19: C-115 | B19: =IFERROR(VLOOKUP(A19, '02_Cashier_Register'!$A$14:$G$28, 2, FALSE), "Unknown") | C19: =IFERROR(VLOOKUP(A19, '02_Cashier_Register'!$A$14:$G$28, 3, FALSE), "Unknown") | D19: =COUNTIFS('03_Raw_POS_Journal'!$F$5:$F$678, A19, '03_Raw_POS_Journal'!$H$5:$H$678, "Sale Tender") | E19: =COUNTIFS('03_Raw_POS_Journal'!$F$5:$F$678, A19, '03_Raw_POS_Journal'!$H$5:$H$678, "Sale Tender", '03_Raw_POS_Journal'!$I$5:$I$678, "Cash") | F19: =COUNTIFS('03_Raw_POS_Journal'!$F$5:$F$678, A19, '03_Raw_POS_Journal'!$H$5:$H$678, "Post-Bill Void") | G19: =COUNTIFS('03_Raw_POS_Journal'!$F$5:$F$678, A19, '03_Raw_POS_Journal'!$H$5:$H$678, "Post-Bill Void", '03_Raw_POS_Journal'!$I$5:$I$678, "Cash") | H19: =IFERROR(IF(E19>0, G19/E19, 0), 0) | I19: =IFERROR(AVERAGEIFS('03_Raw_POS_Journal'!$N$5:$N$678, '03_Raw_POS_Journal'!$F$5:$F$678, A19, '03_Raw_POS_Journal'!$H$5:$H$678, "Post-Bill Void"), 0) | J19: =COUNTIFS('03_Raw_POS_Journal'!$F$5:$F$678, A19, '03_Raw_POS_Journal'!$H$5:$H$678, "Post-Bill Void", '03_Raw_POS_Journal'!$N$5:$N$678, ">120") | K19: =COUNTIFS('03_Raw_POS_Journal'!$F$5:$F$678, A19, '03_Raw_POS_Journal'!$H$5:$H$678, "Post-Bill Void", '03_Raw_POS_Journal'!$I$5:$I$678, "Cash", '03_Raw_POS_Journal'!$N$5:$N$678, ">120") | L19: =SUMIFS('03_Raw_POS_Journal'!$K$5:$K$678, '03_Raw_POS_Journal'!$F$5:$F$678, A19, '03_Raw_POS_Journal'!$H$5:$H$678, "Post-Bill Void", '03_Raw_POS_Journal'!$I$5:$I$678, "Cash") | M19: =IFERROR(IF(_xlfn.STDEV.S($H$5:$H$19)=0, 0, (H19 - AVERAGE($H$5:$H$19)) / _xlfn.STDEV.S($H$5:$H$19)), 0) | N19: =IF(K19>=5, "CRITICAL RISK", IF(OR(K19>=2, M19>=1.5, G19>=5), "ELEVATED RISK", "STANDARD"))
A20: TOTAL / BENCHMARK | D20: =SUM(D5:D19) | E20: =SUM(E5:E19) | F20: =SUM(F5:F19) | G20: =SUM(G5:G19) | H20: =IFERROR(IF(E20>0, G20/E20, 0), 0) | I20: =IFERROR(AVERAGEIFS('03_Raw_POS_Journal'!$N$5:$N$678, '03_Raw_POS_Journal'!$H$5:$H$678, "Post-Bill Void"), 0) | J20: =SUM(J5:J19) | K20: =SUM(K5:K19) | L20: =SUM(L5:L19)

Sheet 05_Engine_Drawer_Kicks
A1: AUDIT ENGINE 2: NO-SALE DRAWER ACTIVITY ANALYSIS
A2: AUTOMATED CALCULATION: Benchmarks unrecorded till openings against peer averages and store baselines to detect off-book cash trade. Steel headers (#2F5597) update dynamically.
A4: Cashier ID | B4: Cashier Name | C4: Branch | D4: Total Paid Sales | E4: No-Sale Drawer Openings | F4: Openings per 100 Sales | G4: Branch Benchmark Rate | H4: Excess Drawer Openings | I4: Avg Ticket Size ($) | J4: Est. Unrecorded Exposure ($) | K4: Opening Rate Z-Score | L4: Drawer Risk Classification
A5: C-101 | B5: =IFERROR(VLOOKUP(A5, '02_Cashier_Register'!$A$14:$G$28, 2, FALSE), "Unknown") | C5: =IFERROR(VLOOKUP(A5, '02_Cashier_Register'!$A$14:$G$28, 3, FALSE), "Unknown") | D5: =COUNTIFS('03_Raw_POS_Journal'!$F$5:$F$678, A5, '03_Raw_POS_Journal'!$H$5:$H$678, "Sale Tender") | E5: =COUNTIFS('03_Raw_POS_Journal'!$F$5:$F$678, A5, '03_Raw_POS_Journal'!$H$5:$H$678, "No-Sale Drawer Opening") | F5: =IFERROR(IF(D5>0, (E5/D5)*100, 0), 0) | G5: =IFERROR(VLOOKUP(C5, '02_Cashier_Register'!$A$6:$F$9, 6, FALSE), 2.0) | H5: =MAX(0, E5 - (D5 * G5 / 100)) | I5: =IFERROR(AVERAGEIFS('03_Raw_POS_Journal'!$K$5:$K$678, '03_Raw_POS_Journal'!$D$5:$D$678, C5, '03_Raw_POS_Journal'!$H$5:$H$678, "Sale Tender"), IFERROR(AVERAGEIFS('03_Raw_POS_Journal'!$K$5:$K$678, '03_Raw_POS_Journal'!$H$5:$H$678, "Sale Tender"), 25.0)) | J5: =H5 * I5 * 0.40 | K5: =IFERROR(IF(_xlfn.STDEV.S($F$5:$F$19)=0, 0, (F5 - AVERAGE($F$5:$F$19)) / _xlfn.STDEV.S($F$5:$F$19)), 0) | L5: =IF(K5>=2.0, "HIGH RISK", IF(K5>=1.0, "ELEVATED RISK", "STANDARD"))
A6: C-102 | B6: =IFERROR(VLOOKUP(A6, '02_Cashier_Register'!$A$14:$G$28, 2, FALSE), "Unknown") | C6: =IFERROR(VLOOKUP(A6, '02_Cashier_Register'!$A$14:$G$28, 3, FALSE), "Unknown") | D6: =COUNTIFS('03_Raw_POS_Journal'!$F$5:$F$678, A6, '03_Raw_POS_Journal'!$H$5:$H$678, "Sale Tender") | E6: =COUNTIFS('03_Raw_POS_Journal'!$F$5:$F$678, A6, '03_Raw_POS_Journal'!$H$5:$H$678, "No-Sale Drawer Opening") | F6: =IFERROR(IF(D6>0, (E6/D6)*100, 0), 0) | G6: =IFERROR(VLOOKUP(C6, '02_Cashier_Register'!$A$6:$F$9, 6, FALSE), 2.0) | H6: =MAX(0, E6 - (D6 * G6 / 100)) | I6: =IFERROR(AVERAGEIFS('03_Raw_POS_Journal'!$K$5:$K$678, '03_Raw_POS_Journal'!$D$5:$D$678, C6, '03_Raw_POS_Journal'!$H$5:$H$678, "Sale Tender"), IFERROR(AVERAGEIFS('03_Raw_POS_Journal'!$K$5:$K$678, '03_Raw_POS_Journal'!$H$5:$H$678, "Sale Tender"), 25.0)) | J6: =H6 * I6 * 0.40 | K6: =IFERROR(IF(_xlfn.STDEV.S($F$5:$F$19)=0, 0, (F6 - AVERAGE($F$5:$F$19)) / _xlfn.STDEV.S($F$5:$F$19)), 0) | L6: =IF(K6>=2.0, "HIGH RISK", IF(K6>=1.0, "ELEVATED RISK", "STANDARD"))
A7: C-103 | B7: =IFERROR(VLOOKUP(A7, '02_Cashier_Register'!$A$14:$G$28, 2, FALSE), "Unknown") | C7: =IFERROR(VLOOKUP(A7, '02_Cashier_Register'!$A$14:$G$28, 3, FALSE), "Unknown") | D7: =COUNTIFS('03_Raw_POS_Journal'!$F$5:$F$678, A7, '03_Raw_POS_Journal'!$H$5:$H$678, "Sale Tender") | E7: =COUNTIFS('03_Raw_POS_Journal'!$F$5:$F$678, A7, '03_Raw_POS_Journal'!$H$5:$H$678, "No-Sale Drawer Opening") | F7: =IFERROR(IF(D7>0, (E7/D7)*100, 0), 0) | G7: =IFERROR(VLOOKUP(C7, '02_Cashier_Register'!$A$6:$F$9, 6, FALSE), 2.0) | H7: =MAX(0, E7 - (D7 * G7 / 100)) | I7: =IFERROR(AVERAGEIFS('03_Raw_POS_Journal'!$K$5:$K$678, '03_Raw_POS_Journal'!$D$5:$D$678, C7, '03_Raw_POS_Journal'!$H$5:$H$678, "Sale Tender"), IFERROR(AVERAGEIFS('03_Raw_POS_Journal'!$K$5:$K$678, '03_Raw_POS_Journal'!$H$5:$H$678, "Sale Tender"), 25.0)) | J7: =H7 * I7 * 0.40 | K7: =IFERROR(IF(_xlfn.STDEV.S($F$5:$F$19)=0, 0, (F7 - AVERAGE($F$5:$F$19)) / _xlfn.STDEV.S($F$5:$F$19)), 0) | L7: =IF(K7>=2.0, "HIGH RISK", IF(K7>=1.0, "ELEVATED RISK", "STANDARD"))
A8: C-104 | B8: =IFERROR(VLOOKUP(A8, '02_Cashier_Register'!$A$14:$G$28, 2, FALSE), "Unknown") | C8: =IFERROR(VLOOKUP(A8, '02_Cashier_Register'!$A$14:$G$28, 3, FALSE), "Unknown") | D8: =COUNTIFS('03_Raw_POS_Journal'!$F$5:$F$678, A8, '03_Raw_POS_Journal'!$H$5:$H$678, "Sale Tender") | E8: =COUNTIFS('03_Raw_POS_Journal'!$F$5:$F$678, A8, '03_Raw_POS_Journal'!$H$5:$H$678, "No-Sale Drawer Opening") | F8: =IFERROR(IF(D8>0, (E8/D8)*100, 0), 0) | G8: =IFERROR(VLOOKUP(C8, '02_Cashier_Register'!$A$6:$F$9, 6, FALSE), 2.0) | H8: =MAX(0, E8 - (D8 * G8 / 100)) | I8: =IFERROR(AVERAGEIFS('03_Raw_POS_Journal'!$K$5:$K$678, '03_Raw_POS_Journal'!$D$5:$D$678, C8, '03_Raw_POS_Journal'!$H$5:$H$678, "Sale Tender"), IFERROR(AVERAGEIFS('03_Raw_POS_Journal'!$K$5:$K$678, '03_Raw_POS_Journal'!$H$5:$H$678, "Sale Tender"), 25.0)) | J8: =H8 * I8 * 0.40 | K8: =IFERROR(IF(_xlfn.STDEV.S($F$5:$F$19)=0, 0, (F8 - AVERAGE($F$5:$F$19)) / _xlfn.STDEV.S($F$5:$F$19)), 0) | L8: =IF(K8>=2.0, "HIGH RISK", IF(K8>=1.0, "ELEVATED RISK", "STANDARD"))
A9: C-105 | B9: =IFERROR(VLOOKUP(A9, '02_Cashier_Register'!$A$14:$G$28, 2, FALSE), "Unknown") | C9: =IFERROR(VLOOKUP(A9, '02_Cashier_Register'!$A$14:$G$28, 3, FALSE), "Unknown") | D9: =COUNTIFS('03_Raw_POS_Journal'!$F$5:$F$678, A9, '03_Raw_POS_Journal'!$H$5:$H$678, "Sale Tender") | E9: =COUNTIFS('03_Raw_POS_Journal'!$F$5:$F$678, A9, '03_Raw_POS_Journal'!$H$5:$H$678, "No-Sale Drawer Opening") | F9: =IFERROR(IF(D9>0, (E9/D9)*100, 0), 0) | G9: =IFERROR(VLOOKUP(C9, '02_Cashier_Register'!$A$6:$F$9, 6, FALSE), 2.0) | H9: =MAX(0, E9 - (D9 * G9 / 100)) | I9: =IFERROR(AVERAGEIFS('03_Raw_POS_Journal'!$K$5:$K$678, '03_Raw_POS_Journal'!$D$5:$D$678, C9, '03_Raw_POS_Journal'!$H$5:$H$678, "Sale Tender"), IFERROR(AVERAGEIFS('03_Raw_POS_Journal'!$K$5:$K$678, '03_Raw_POS_Journal'!$H$5:$H$678, "Sale Tender"), 25.0)) | J9: =H9 * I9 * 0.40 | K9: =IFERROR(IF(_xlfn.STDEV.S($F$5:$F$19)=0, 0, (F9 - AVERAGE($F$5:$F$19)) / _xlfn.STDEV.S($F$5:$F$19)), 0) | L9: =IF(K9>=2.0, "HIGH RISK", IF(K9>=1.0, "ELEVATED RISK", "STANDARD"))
A10: C-106 | B10: =IFERROR(VLOOKUP(A10, '02_Cashier_Register'!$A$14:$G$28, 2, FALSE), "Unknown") | C10: =IFERROR(VLOOKUP(A10, '02_Cashier_Register'!$A$14:$G$28, 3, FALSE), "Unknown") | D10: =COUNTIFS('03_Raw_POS_Journal'!$F$5:$F$678, A10, '03_Raw_POS_Journal'!$H$5:$H$678, "Sale Tender") | E10: =COUNTIFS('03_Raw_POS_Journal'!$F$5:$F$678, A10, '03_Raw_POS_Journal'!$H$5:$H$678, "No-Sale Drawer Opening") | F10: =IFERROR(IF(D10>0, (E10/D10)*100, 0), 0) | G10: =IFERROR(VLOOKUP(C10, '02_Cashier_Register'!$A$6:$F$9, 6, FALSE), 2.0) | H10: =MAX(0, E10 - (D10 * G10 / 100)) | I10: =IFERROR(AVERAGEIFS('03_Raw_POS_Journal'!$K$5:$K$678, '03_Raw_POS_Journal'!$D$5:$D$678, C10, '03_Raw_POS_Journal'!$H$5:$H$678, "Sale Tender"), IFERROR(AVERAGEIFS('03_Raw_POS_Journal'!$K$5:$K$678, '03_Raw_POS_Journal'!$H$5:$H$678, "Sale Tender"), 25.0)) | J10: =H10 * I10 * 0.40 | K10: =IFERROR(IF(_xlfn.STDEV.S($F$5:$F$19)=0, 0, (F10 - AVERAGE($F$5:$F$19)) / _xlfn.STDEV.S($F$5:$F$19)), 0) | L10: =IF(K10>=2.0, "HIGH RISK", IF(K10>=1.0, "ELEVATED RISK", "STANDARD"))
A11: C-107 | B11: =IFERROR(VLOOKUP(A11, '02_Cashier_Register'!$A$14:$G$28, 2, FALSE), "Unknown") | C11: =IFERROR(VLOOKUP(A11, '02_Cashier_Register'!$A$14:$G$28, 3, FALSE), "Unknown") | D11: =COUNTIFS('03_Raw_POS_Journal'!$F$5:$F$678, A11, '03_Raw_POS_Journal'!$H$5:$H$678, "Sale Tender") | E11: =COUNTIFS('03_Raw_POS_Journal'!$F$5:$F$678, A11, '03_Raw_POS_Journal'!$H$5:$H$678, "No-Sale Drawer Opening") | F11: =IFERROR(IF(D11>0, (E11/D11)*100, 0), 0) | G11: =IFERROR(VLOOKUP(C11, '02_Cashier_Register'!$A$6:$F$9, 6, FALSE), 2.0) | H11: =MAX(0, E11 - (D11 * G11 / 100)) | I11: =IFERROR(AVERAGEIFS('03_Raw_POS_Journal'!$K$5:$K$678, '03_Raw_POS_Journal'!$D$5:$D$678, C11, '03_Raw_POS_Journal'!$H$5:$H$678, "Sale Tender"), IFERROR(AVERAGEIFS('03_Raw_POS_Journal'!$K$5:$K$678, '03_Raw_POS_Journal'!$H$5:$H$678, "Sale Tender"), 25.0)) | J11: =H11 * I11 * 0.40 | K11: =IFERROR(IF(_xlfn.STDEV.S($F$5:$F$19)=0, 0, (F11 - AVERAGE($F$5:$F$19)) / _xlfn.STDEV.S($F$5:$F$19)), 0) | L11: =IF(K11>=2.0, "HIGH RISK", IF(K11>=1.0, "ELEVATED RISK", "STANDARD"))
A12: C-108 | B12: =IFERROR(VLOOKUP(A12, '02_Cashier_Register'!$A$14:$G$28, 2, FALSE), "Unknown") | C12: =IFERROR(VLOOKUP(A12, '02_Cashier_Register'!$A$14:$G$28, 3, FALSE), "Unknown") | D12: =COUNTIFS('03_Raw_POS_Journal'!$F$5:$F$678, A12, '03_Raw_POS_Journal'!$H$5:$H$678, "Sale Tender") | E12: =COUNTIFS('03_Raw_POS_Journal'!$F$5:$F$678, A12, '03_Raw_POS_Journal'!$H$5:$H$678, "No-Sale Drawer Opening") | F12: =IFERROR(IF(D12>0, (E12/D12)*100, 0), 0) | G12: =IFERROR(VLOOKUP(C12, '02_Cashier_Register'!$A$6:$F$9, 6, FALSE), 2.0) | H12: =MAX(0, E12 - (D12 * G12 / 100)) | I12: =IFERROR(AVERAGEIFS('03_Raw_POS_Journal'!$K$5:$K$678, '03_Raw_POS_Journal'!$D$5:$D$678, C12, '03_Raw_POS_Journal'!$H$5:$H$678, "Sale Tender"), IFERROR(AVERAGEIFS('03_Raw_POS_Journal'!$K$5:$K$678, '03_Raw_POS_Journal'!$H$5:$H$678, "Sale Tender"), 25.0)) | J12: =H12 * I12 * 0.40 | K12: =IFERROR(IF(_xlfn.STDEV.S($F$5:$F$19)=0, 0, (F12 - AVERAGE($F$5:$F$19)) / _xlfn.STDEV.S($F$5:$F$19)), 0) | L12: =IF(K12>=2.0, "HIGH RISK", IF(K12>=1.0, "ELEVATED RISK", "STANDARD"))
A13: C-109 | B13: =IFERROR(VLOOKUP(A13, '02_Cashier_Register'!$A$14:$G$28, 2, FALSE), "Unknown") | C13: =IFERROR(VLOOKUP(A13, '02_Cashier_Register'!$A$14:$G$28, 3, FALSE), "Unknown") | D13: =COUNTIFS('03_Raw_POS_Journal'!$F$5:$F$678, A13, '03_Raw_POS_Journal'!$H$5:$H$678, "Sale Tender") | E13: =COUNTIFS('03_Raw_POS_Journal'!$F$5:$F$678, A13, '03_Raw_POS_Journal'!$H$5:$H$678, "No-Sale Drawer Opening") | F13: =IFERROR(IF(D13>0, (E13/D13)*100, 0), 0) | G13: =IFERROR(VLOOKUP(C13, '02_Cashier_Register'!$A$6:$F$9, 6, FALSE), 2.0) | H13: =MAX(0, E13 - (D13 * G13 / 100)) | I13: =IFERROR(AVERAGEIFS('03_Raw_POS_Journal'!$K$5:$K$678, '03_Raw_POS_Journal'!$D$5:$D$678, C13, '03_Raw_POS_Journal'!$H$5:$H$678, "Sale Tender"), IFERROR(AVERAGEIFS('03_Raw_POS_Journal'!$K$5:$K$678, '03_Raw_POS_Journal'!$H$5:$H$678, "Sale Tender"), 25.0)) | J13: =H13 * I13 * 0.40 | K13: =IFERROR(IF(_xlfn.STDEV.S($F$5:$F$19)=0, 0, (F13 - AVERAGE($F$5:$F$19)) / _xlfn.STDEV.S($F$5:$F$19)), 0) | L13: =IF(K13>=2.0, "HIGH RISK", IF(K13>=1.0, "ELEVATED RISK", "STANDARD"))
A14: C-110 | B14: =IFERROR(VLOOKUP(A14, '02_Cashier_Register'!$A$14:$G$28, 2, FALSE), "Unknown") | C14: =IFERROR(VLOOKUP(A14, '02_Cashier_Register'!$A$14:$G$28, 3, FALSE), "Unknown") | D14: =COUNTIFS('03_Raw_POS_Journal'!$F$5:$F$678, A14, '03_Raw_POS_Journal'!$H$5:$H$678, "Sale Tender") | E14: =COUNTIFS('03_Raw_POS_Journal'!$F$5:$F$678, A14, '03_Raw_POS_Journal'!$H$5:$H$678, "No-Sale Drawer Opening") | F14: =IFERROR(IF(D14>0, (E14/D14)*100, 0), 0) | G14: =IFERROR(VLOOKUP(C14, '02_Cashier_Register'!$A$6:$F$9, 6, FALSE), 2.0) | H14: =MAX(0, E14 - (D14 * G14 / 100)) | I14: =IFERROR(AVERAGEIFS('03_Raw_POS_Journal'!$K$5:$K$678, '03_Raw_POS_Journal'!$D$5:$D$678, C14, '03_Raw_POS_Journal'!$H$5:$H$678, "Sale Tender"), IFERROR(AVERAGEIFS('03_Raw_POS_Journal'!$K$5:$K$678, '03_Raw_POS_Journal'!$H$5:$H$678, "Sale Tender"), 25.0)) | J14: =H14 * I14 * 0.40 | K14: =IFERROR(IF(_xlfn.STDEV.S($F$5:$F$19)=0, 0, (F14 - AVERAGE($F$5:$F$19)) / _xlfn.STDEV.S($F$5:$F$19)), 0) | L14: =IF(K14>=2.0, "HIGH RISK", IF(K14>=1.0, "ELEVATED RISK", "STANDARD"))
A15: C-111 | B15: =IFERROR(VLOOKUP(A15, '02_Cashier_Register'!$A$14:$G$28, 2, FALSE), "Unknown") | C15: =IFERROR(VLOOKUP(A15, '02_Cashier_Register'!$A$14:$G$28, 3, FALSE), "Unknown") | D15: =COUNTIFS('03_Raw_POS_Journal'!$F$5:$F$678, A15, '03_Raw_POS_Journal'!$H$5:$H$678, "Sale Tender") | E15: =COUNTIFS('03_Raw_POS_Journal'!$F$5:$F$678, A15, '03_Raw_POS_Journal'!$H$5:$H$678, "No-Sale Drawer Opening") | F15: =IFERROR(IF(D15>0, (E15/D15)*100, 0), 0) | G15: =IFERROR(VLOOKUP(C15, '02_Cashier_Register'!$A$6:$F$9, 6, FALSE), 2.0) | H15: =MAX(0, E15 - (D15 * G15 / 100)) | I15: =IFERROR(AVERAGEIFS('03_Raw_POS_Journal'!$K$5:$K$678, '03_Raw_POS_Journal'!$D$5:$D$678, C15, '03_Raw_POS_Journal'!$H$5:$H$678, "Sale Tender"), IFERROR(AVERAGEIFS('03_Raw_POS_Journal'!$K$5:$K$678, '03_Raw_POS_Journal'!$H$5:$H$678, "Sale Tender"), 25.0)) | J15: =H15 * I15 * 0.40 | K15: =IFERROR(IF(_xlfn.STDEV.S($F$5:$F$19)=0, 0, (F15 - AVERAGE($F$5:$F$19)) / _xlfn.STDEV.S($F$5:$F$19)), 0) | L15: =IF(K15>=2.0, "HIGH RISK", IF(K15>=1.0, "ELEVATED RISK", "STANDARD"))
A16: C-112 | B16: =IFERROR(VLOOKUP(A16, '02_Cashier_Register'!$A$14:$G$28, 2, FALSE), "Unknown") | C16: =IFERROR(VLOOKUP(A16, '02_Cashier_Register'!$A$14:$G$28, 3, FALSE), "Unknown") | D16: =COUNTIFS('03_Raw_POS_Journal'!$F$5:$F$678, A16, '03_Raw_POS_Journal'!$H$5:$H$678, "Sale Tender") | E16: =COUNTIFS('03_Raw_POS_Journal'!$F$5:$F$678, A16, '03_Raw_POS_Journal'!$H$5:$H$678, "No-Sale Drawer Opening") | F16: =IFERROR(IF(D16>0, (E16/D16)*100, 0), 0) | G16: =IFERROR(VLOOKUP(C16, '02_Cashier_Register'!$A$6:$F$9, 6, FALSE), 2.0) | H16: =MAX(0, E16 - (D16 * G16 / 100)) | I16: =IFERROR(AVERAGEIFS('03_Raw_POS_Journal'!$K$5:$K$678, '03_Raw_POS_Journal'!$D$5:$D$678, C16, '03_Raw_POS_Journal'!$H$5:$H$678, "Sale Tender"), IFERROR(AVERAGEIFS('03_Raw_POS_Journal'!$K$5:$K$678, '03_Raw_POS_Journal'!$H$5:$H$678, "Sale Tender"), 25.0)) | J16: =H16 * I16 * 0.40 | K16: =IFERROR(IF(_xlfn.STDEV.S($F$5:$F$19)=0, 0, (F16 - AVERAGE($F$5:$F$19)) / _xlfn.STDEV.S($F$5:$F$19)), 0) | L16: =IF(K16>=2.0, "HIGH RISK", IF(K16>=1.0, "ELEVATED RISK", "STANDARD"))
... A19: C-115 | B19: =IFERROR(VLOOKUP(A19, '02_Cashier_Register'!$A$14:$G$28, 2, FALSE), "Unknown") | C19: =IFERROR(VLOOKUP(A19, '02_Cashier_Register'!$A$14:$G$28, 3, FALSE), "Unknown") | D19: =COUNTIFS('03_Raw_POS_Journal'!$F$5:$F$678, A19, '03_Raw_POS_Journal'!$H$5:$H$678, "Sale Tender") | E19: =COUNTIFS('03_Raw_POS_Journal'!$F$5:$F$678, A19, '03_Raw_POS_Journal'!$H$5:$H$678, "No-Sale Drawer Opening") | F19: =IFERROR(IF(D19>0, (E19/D19)*100, 0), 0) | G19: =IFERROR(VLOOKUP(C19, '02_Cashier_Register'!$A$6:$F$9, 6, FALSE), 2.0) | H19: =MAX(0, E19 - (D19 * G19 / 100)) | I19: =IFERROR(AVERAGEIFS('03_Raw_POS_Journal'!$K$5:$K$678, '03_Raw_POS_Journal'!$D$5:$D$678, C19, '03_Raw_POS_Journal'!$H$5:$H$678, "Sale Tender"), IFERROR(AVERAGEIFS('03_Raw_POS_Journal'!$K$5:$K$678, '03_Raw_POS_Journal'!$H$5:$H$678, "Sale Tender"), 25.0)) | J19: =H19 * I19 * 0.40 | K19: =IFERROR(IF(_xlfn.STDEV.S($F$5:$F$19)=0, 0, (F19 - AVERAGE($F$5:$F$19)) / _xlfn.STDEV.S($F$5:$F$19)), 0) | L19: =IF(K19>=2.0, "HIGH RISK", IF(K19>=1.0, "ELEVATED RISK", "STANDARD"))
A20: TOTAL / BENCHMARK | D20: =SUM(D5:D19) | E20: =SUM(E5:E19) | F20: =IFERROR(IF(D20>0, (E20/D20)*100, 0), 0) | H20: =SUM(H5:H19) | J20: =SUM(J5:J19)

Sheet 06_Engine_Overrides
A1: AUDIT ENGINE 3: LINE-ITEM VOIDS & SUPERVISORY AUTHORIZATIONS
A2: AUTOMATED CALCULATION: Analyzes pre-settlement line item deletions and evaluates supervisor credential concentration and terminal concurrency. Steel headers (#2F5597) update dynamically.
A4: PART 1: CASHIER PRE-SETTLEMENT LINE ITEM DELETIONS
A5: Cashier ID | B5: Cashier Name | C5: Branch | D5: Total Line Voids | E5: Cash Line Voids | F5: Total Line Void $ | G5: Cash Line Void $ | H5: Cash Line Void Ratio % | I5: Line Void Z-Score | J5: Line Void Risk Classification | K5: Total Overrides | L5: Concurrent Overrides | M5: Supervisor Authorization Tier
A6: C-101 | B6: =IFERROR(VLOOKUP(A6, '02_Cashier_Register'!$A$14:$G$28, 2, FALSE), "Unknown") | C6: =IFERROR(VLOOKUP(A6, '02_Cashier_Register'!$A$14:$G$28, 3, FALSE), "Unknown") | D6: =COUNTIFS('03_Raw_POS_Journal'!$F$5:$F$678, A6, '03_Raw_POS_Journal'!$H$5:$H$678, "Line Item Void") | E6: =COUNTIFS('03_Raw_POS_Journal'!$F$5:$F$678, A6, '03_Raw_POS_Journal'!$H$5:$H$678, "Line Item Void", '03_Raw_POS_Journal'!$I$5:$I$678, "Cash") | F6: =SUMIFS('03_Raw_POS_Journal'!$K$5:$K$678, '03_Raw_POS_Journal'!$F$5:$F$678, A6, '03_Raw_POS_Journal'!$H$5:$H$678, "Line Item Void") | G6: =SUMIFS('03_Raw_POS_Journal'!$K$5:$K$678, '03_Raw_POS_Journal'!$F$5:$F$678, A6, '03_Raw_POS_Journal'!$H$5:$H$678, "Line Item Void", '03_Raw_POS_Journal'!$I$5:$I$678, "Cash") | H6: =IFERROR(IF(D6>0, E6/D6, 0), 0) | I6: =IFERROR(IF(_xlfn.STDEV.S($E$6:$E$20)=0, 0, (E6 - AVERAGE($E$6:$E$20)) / _xlfn.STDEV.S($E$6:$E$20)), 0) | J6: =IF(I6>=2.0, "HIGH RISK", IF(I6>=1.0, "ELEVATED RISK", "STANDARD")) | K6: =COUNTIFS('03_Raw_POS_Journal'!$F$5:$F$678, A6, '03_Raw_POS_Journal'!$G$5:$G$678, "<>NONE") | L6: =IF(AND(ISNUMBER(SEARCH("COLLUSION", INDEX($I$25:$I$28, MATCH(C6, $C$25:$C$28, 0)))), ISNUMBER(SEARCH(A6, INDEX($F$25:$F$28, MATCH(C6, $C$25:$C$28, 0))))), COUNTIFS('03_Raw_POS_Journal'!$F$5:$F$678, A6, '03_Raw_POS_Journal'!$G$5:$G$678, INDEX($A$25:$A$28, MATCH(C6, $C$25:$C$28, 0))), 0) | M6: =IF(L6>=10, "HIGH CONCURRENCY", IF(L6>=3, "WATCHLIST", "STANDARD"))
A7: C-102 | B7: =IFERROR(VLOOKUP(A7, '02_Cashier_Register'!$A$14:$G$28, 2, FALSE), "Unknown") | C7: =IFERROR(VLOOKUP(A7, '02_Cashier_Register'!$A$14:$G$28, 3, FALSE), "Unknown") | D7: =COUNTIFS('03_Raw_POS_Journal'!$F$5:$F$678, A7, '03_Raw_POS_Journal'!$H$5:$H$678, "Line Item Void") | E7: =COUNTIFS('03_Raw_POS_Journal'!$F$5:$F$678, A7, '03_Raw_POS_Journal'!$H$5:$H$678, "Line Item Void", '03_Raw_POS_Journal'!$I$5:$I$678, "Cash") | F7: =SUMIFS('03_Raw_POS_Journal'!$K$5:$K$678, '03_Raw_POS_Journal'!$F$5:$F$678, A7, '03_Raw_POS_Journal'!$H$5:$H$678, "Line Item Void") | G7: =SUMIFS('03_Raw_POS_Journal'!$K$5:$K$678, '03_Raw_POS_Journal'!$F$5:$F$678, A7, '03_Raw_POS_Journal'!$H$5:$H$678, "Line Item Void", '03_Raw_POS_Journal'!$I$5:$I$678, "Cash") | H7: =IFERROR(IF(D7>0, E7/D7, 0), 0) | I7: =IFERROR(IF(_xlfn.STDEV.S($E$6:$E$20)=0, 0, (E7 - AVERAGE($E$6:$E$20)) / _xlfn.STDEV.S($E$6:$E$20)), 0) | J7: =IF(I7>=2.0, "HIGH RISK", IF(I7>=1.0, "ELEVATED RISK", "STANDARD")) | K7: =COUNTIFS('03_Raw_POS_Journal'!$F$5:$F$678, A7, '03_Raw_POS_Journal'!$G$5:$G$678, "<>NONE") | L7: =IF(AND(ISNUMBER(SEARCH("COLLUSION", INDEX($I$25:$I$28, MATCH(C7, $C$25:$C$28, 0)))), ISNUMBER(SEARCH(A7, INDEX($F$25:$F$28, MATCH(C7, $C$25:$C$28, 0))))), COUNTIFS('03_Raw_POS_Journal'!$F$5:$F$678, A7, '03_Raw_POS_Journal'!$G$5:$G$678, INDEX($A$25:$A$28, MATCH(C7, $C$25:$C$28, 0))), 0) | M7: =IF(L7>=10, "HIGH CONCURRENCY", IF(L7>=3, "WATCHLIST", "STANDARD"))
A8: C-103 | B8: =IFERROR(VLOOKUP(A8, '02_Cashier_Register'!$A$14:$G$28, 2, FALSE), "Unknown") | C8: =IFERROR(VLOOKUP(A8, '02_Cashier_Register'!$A$14:$G$28, 3, FALSE), "Unknown") | D8: =COUNTIFS('03_Raw_POS_Journal'!$F$5:$F$678, A8, '03_Raw_POS_Journal'!$H$5:$H$678, "Line Item Void") | E8: =COUNTIFS('03_Raw_POS_Journal'!$F$5:$F$678, A8, '03_Raw_POS_Journal'!$H$5:$H$678, "Line Item Void", '03_Raw_POS_Journal'!$I$5:$I$678, "Cash") | F8: =SUMIFS('03_Raw_POS_Journal'!$K$5:$K$678, '03_Raw_POS_Journal'!$F$5:$F$678, A8, '03_Raw_POS_Journal'!$H$5:$H$678, "Line Item Void") | G8: =SUMIFS('03_Raw_POS_Journal'!$K$5:$K$678, '03_Raw_POS_Journal'!$F$5:$F$678, A8, '03_Raw_POS_Journal'!$H$5:$H$678, "Line Item Void", '03_Raw_POS_Journal'!$I$5:$I$678, "Cash") | H8: =IFERROR(IF(D8>0, E8/D8, 0), 0) | I8: =IFERROR(IF(_xlfn.STDEV.S($E$6:$E$20)=0, 0, (E8 - AVERAGE($E$6:$E$20)) / _xlfn.STDEV.S($E$6:$E$20)), 0) | J8: =IF(I8>=2.0, "HIGH RISK", IF(I8>=1.0, "ELEVATED RISK", "STANDARD")) | K8: =COUNTIFS('03_Raw_POS_Journal'!$F$5:$F$678, A8, '03_Raw_POS_Journal'!$G$5:$G$678, "<>NONE") | L8: =IF(AND(ISNUMBER(SEARCH("COLLUSION", INDEX($I$25:$I$28, MATCH(C8, $C$25:$C$28, 0)))), ISNUMBER(SEARCH(A8, INDEX($F$25:$F$28, MATCH(C8, $C$25:$C$28, 0))))), COUNTIFS('03_Raw_POS_Journal'!$F$5:$F$678, A8, '03_Raw_POS_Journal'!$G$5:$G$678, INDEX($A$25:$A$28, MATCH(C8, $C$25:$C$28, 0))), 0) | M8: =IF(L8>=10, "HIGH CONCURRENCY", IF(L8>=3, "WATCHLIST", "STANDARD"))
A9: C-104 | B9: =IFERROR(VLOOKUP(A9, '02_Cashier_Register'!$A$14:$G$28, 2, FALSE), "Unknown") | C9: =IFERROR(VLOOKUP(A9, '02_Cashier_Register'!$A$14:$G$28, 3, FALSE), "Unknown") | D9: =COUNTIFS('03_Raw_POS_Journal'!$F$5:$F$678, A9, '03_Raw_POS_Journal'!$H$5:$H$678, "Line Item Void") | E9: =COUNTIFS('03_Raw_POS_Journal'!$F$5:$F$678, A9, '03_Raw_POS_Journal'!$H$5:$H$678, "Line Item Void", '03_Raw_POS_Journal'!$I$5:$I$678, "Cash") | F9: =SUMIFS('03_Raw_POS_Journal'!$K$5:$K$678, '03_Raw_POS_Journal'!$F$5:$F$678, A9, '03_Raw_POS_Journal'!$H$5:$H$678, "Line Item Void") | G9: =SUMIFS('03_Raw_POS_Journal'!$K$5:$K$678, '03_Raw_POS_Journal'!$F$5:$F$678, A9, '03_Raw_POS_Journal'!$H$5:$H$678, "Line Item Void", '03_Raw_POS_Journal'!$I$5:$I$678, "Cash") | H9: =IFERROR(IF(D9>0, E9/D9, 0), 0) | I9: =IFERROR(IF(_xlfn.STDEV.S($E$6:$E$20)=0, 0, (E9 - AVERAGE($E$6:$E$20)) / _xlfn.STDEV.S($E$6:$E$20)), 0) | J9: =IF(I9>=2.0, "HIGH RISK", IF(I9>=1.0, "ELEVATED RISK", "STANDARD")) | K9: =COUNTIFS('03_Raw_POS_Journal'!$F$5:$F$678, A9, '03_Raw_POS_Journal'!$G$5:$G$678, "<>NONE") | L9: =IF(AND(ISNUMBER(SEARCH("COLLUSION", INDEX($I$25:$I$28, MATCH(C9, $C$25:$C$28, 0)))), ISNUMBER(SEARCH(A9, INDEX($F$25:$F$28, MATCH(C9, $C$25:$C$28, 0))))), COUNTIFS('03_Raw_POS_Journal'!$F$5:$F$678, A9, '03_Raw_POS_Journal'!$G$5:$G$678, INDEX($A$25:$A$28, MATCH(C9, $C$25:$C$28, 0))), 0) | M9: =IF(L9>=10, "HIGH CONCURRENCY", IF(L9>=3, "WATCHLIST", "STANDARD"))
A10: C-105 | B10: =IFERROR(VLOOKUP(A10, '02_Cashier_Register'!$A$14:$G$28, 2, FALSE), "Unknown") | C10: =IFERROR(VLOOKUP(A10, '02_Cashier_Register'!$A$14:$G$28, 3, FALSE), "Unknown") | D10: =COUNTIFS('03_Raw_POS_Journal'!$F$5:$F$678, A10, '03_Raw_POS_Journal'!$H$5:$H$678, "Line Item Void") | E10: =COUNTIFS('03_Raw_POS_Journal'!$F$5:$F$678, A10, '03_Raw_POS_Journal'!$H$5:$H$678, "Line Item Void", '03_Raw_POS_Journal'!$I$5:$I$678, "Cash") | F10: =SUMIFS('03_Raw_POS_Journal'!$K$5:$K$678, '03_Raw_POS_Journal'!$F$5:$F$678, A10, '03_Raw_POS_Journal'!$H$5:$H$678, "Line Item Void") | G10: =SUMIFS('03_Raw_POS_Journal'!$K$5:$K$678, '03_Raw_POS_Journal'!$F$5:$F$678, A10, '03_Raw_POS_Journal'!$H$5:$H$678, "Line Item Void", '03_Raw_POS_Journal'!$I$5:$I$678, "Cash") | H10: =IFERROR(IF(D10>0, E10/D10, 0), 0) | I10: =IFERROR(IF(_xlfn.STDEV.S($E$6:$E$20)=0, 0, (E10 - AVERAGE($E$6:$E$20)) / _xlfn.STDEV.S($E$6:$E$20)), 0) | J10: =IF(I10>=2.0, "HIGH RISK", IF(I10>=1.0, "ELEVATED RISK", "STANDARD")) | K10: =COUNTIFS('03_Raw_POS_Journal'!$F$5:$F$678, A10, '03_Raw_POS_Journal'!$G$5:$G$678, "<>NONE") | L10: =IF(AND(ISNUMBER(SEARCH("COLLUSION", INDEX($I$25:$I$28, MATCH(C10, $C$25:$C$28, 0)))), ISNUMBER(SEARCH(A10, INDEX($F$25:$F$28, MATCH(C10, $C$25:$C$28, 0))))), COUNTIFS('03_Raw_POS_Journal'!$F$5:$F$678, A10, '03_Raw_POS_Journal'!$G$5:$G$678, INDEX($A$25:$A$28, MATCH(C10, $C$25:$C$28, 0))), 0) | M10: =IF(L10>=10, "HIGH CONCURRENCY", IF(L10>=3, "WATCHLIST", "STANDARD"))
A11: C-106 | B11: =IFERROR(VLOOKUP(A11, '02_Cashier_Register'!$A$14:$G$28, 2, FALSE), "Unknown") | C11: =IFERROR(VLOOKUP(A11, '02_Cashier_Register'!$A$14:$G$28, 3, FALSE), "Unknown") | D11: =COUNTIFS('03_Raw_POS_Journal'!$F$5:$F$678, A11, '03_Raw_POS_Journal'!$H$5:$H$678, "Line Item Void") | E11: =COUNTIFS('03_Raw_POS_Journal'!$F$5:$F$678, A11, '03_Raw_POS_Journal'!$H$5:$H$678, "Line Item Void", '03_Raw_POS_Journal'!$I$5:$I$678, "Cash") | F11: =SUMIFS('03_Raw_POS_Journal'!$K$5:$K$678, '03_Raw_POS_Journal'!$F$5:$F$678, A11, '03_Raw_POS_Journal'!$H$5:$H$678, "Line Item Void") | G11: =SUMIFS('03_Raw_POS_Journal'!$K$5:$K$678, '03_Raw_POS_Journal'!$F$5:$F$678, A11, '03_Raw_POS_Journal'!$H$5:$H$678, "Line Item Void", '03_Raw_POS_Journal'!$I$5:$I$678, "Cash") | H11: =IFERROR(IF(D11>0, E11/D11, 0), 0) | I11: =IFERROR(IF(_xlfn.STDEV.S($E$6:$E$20)=0, 0, (E11 - AVERAGE($E$6:$E$20)) / _xlfn.STDEV.S($E$6:$E$20)), 0) | J11: =IF(I11>=2.0, "HIGH RISK", IF(I11>=1.0, "ELEVATED RISK", "STANDARD")) | K11: =COUNTIFS('03_Raw_POS_Journal'!$F$5:$F$678, A11, '03_Raw_POS_Journal'!$G$5:$G$678, "<>NONE") | L11: =IF(AND(ISNUMBER(SEARCH("COLLUSION", INDEX($I$25:$I$28, MATCH(C11, $C$25:$C$28, 0)))), ISNUMBER(SEARCH(A11, INDEX($F$25:$F$28, MATCH(C11, $C$25:$C$28, 0))))), COUNTIFS('03_Raw_POS_Journal'!$F$5:$F$678, A11, '03_Raw_POS_Journal'!$G$5:$G$678, INDEX($A$25:$A$28, MATCH(C11, $C$25:$C$28, 0))), 0) | M11: =IF(L11>=10, "HIGH CONCURRENCY", IF(L11>=3, "WATCHLIST", "STANDARD"))
A12: C-107 | B12: =IFERROR(VLOOKUP(A12, '02_Cashier_Register'!$A$14:$G$28, 2, FALSE), "Unknown") | C12: =IFERROR(VLOOKUP(A12, '02_Cashier_Register'!$A$14:$G$28, 3, FALSE), "Unknown") | D12: =COUNTIFS('03_Raw_POS_Journal'!$F$5:$F$678, A12, '03_Raw_POS_Journal'!$H$5:$H$678, "Line Item Void") | E12: =COUNTIFS('03_Raw_POS_Journal'!$F$5:$F$678, A12, '03_Raw_POS_Journal'!$H$5:$H$678, "Line Item Void", '03_Raw_POS_Journal'!$I$5:$I$678, "Cash") | F12: =SUMIFS('03_Raw_POS_Journal'!$K$5:$K$678, '03_Raw_POS_Journal'!$F$5:$F$678, A12, '03_Raw_POS_Journal'!$H$5:$H$678, "Line Item Void") | G12: =SUMIFS('03_Raw_POS_Journal'!$K$5:$K$678, '03_Raw_POS_Journal'!$F$5:$F$678, A12, '03_Raw_POS_Journal'!$H$5:$H$678, "Line Item Void", '03_Raw_POS_Journal'!$I$5:$I$678, "Cash") | H12: =IFERROR(IF(D12>0, E12/D12, 0), 0) | I12: =IFERROR(IF(_xlfn.STDEV.S($E$6:$E$20)=0, 0, (E12 - AVERAGE($E$6:$E$20)) / _xlfn.STDEV.S($E$6:$E$20)), 0) | J12: =IF(I12>=2.0, "HIGH RISK", IF(I12>=1.0, "ELEVATED RISK", "STANDARD")) | K12: =COUNTIFS('03_Raw_POS_Journal'!$F$5:$F$678, A12, '03_Raw_POS_Journal'!$G$5:$G$678, "<>NONE") | L12: =IF(AND(ISNUMBER(SEARCH("COLLUSION", INDEX($I$25:$I$28, MATCH(C12, $C$25:$C$28, 0)))), ISNUMBER(SEARCH(A12, INDEX($F$25:$F$28, MATCH(C12, $C$25:$C$28, 0))))), COUNTIFS('03_Raw_POS_Journal'!$F$5:$F$678, A12, '03_Raw_POS_Journal'!$G$5:$G$678, INDEX($A$25:$A$28, MATCH(C12, $C$25:$C$28, 0))), 0) | M12: =IF(L12>=10, "HIGH CONCURRENCY", IF(L12>=3, "WATCHLIST", "STANDARD"))
A13: C-108 | B13: =IFERROR(VLOOKUP(A13, '02_Cashier_Register'!$A$14:$G$28, 2, FALSE), "Unknown") | C13: =IFERROR(VLOOKUP(A13, '02_Cashier_Register'!$A$14:$G$28, 3, FALSE), "Unknown") | D13: =COUNTIFS('03_Raw_POS_Journal'!$F$5:$F$678, A13, '03_Raw_POS_Journal'!$H$5:$H$678, "Line Item Void") | E13: =COUNTIFS('03_Raw_POS_Journal'!$F$5:$F$678, A13, '03_Raw_POS_Journal'!$H$5:$H$678, "Line Item Void", '03_Raw_POS_Journal'!$I$5:$I$678, "Cash") | F13: =SUMIFS('03_Raw_POS_Journal'!$K$5:$K$678, '03_Raw_POS_Journal'!$F$5:$F$678, A13, '03_Raw_POS_Journal'!$H$5:$H$678, "Line Item Void") | G13: =SUMIFS('03_Raw_POS_Journal'!$K$5:$K$678, '03_Raw_POS_Journal'!$F$5:$F$678, A13, '03_Raw_POS_Journal'!$H$5:$H$678, "Line Item Void", '03_Raw_POS_Journal'!$I$5:$I$678, "Cash") | H13: =IFERROR(IF(D13>0, E13/D13, 0), 0) | I13: =IFERROR(IF(_xlfn.STDEV.S($E$6:$E$20)=0, 0, (E13 - AVERAGE($E$6:$E$20)) / _xlfn.STDEV.S($E$6:$E$20)), 0) | J13: =IF(I13>=2.0, "HIGH RISK", IF(I13>=1.0, "ELEVATED RISK", "STANDARD")) | K13: =COUNTIFS('03_Raw_POS_Journal'!$F$5:$F$678, A13, '03_Raw_POS_Journal'!$G$5:$G$678, "<>NONE") | L13: =IF(AND(ISNUMBER(SEARCH("COLLUSION", INDEX($I$25:$I$28, MATCH(C13, $C$25:$C$28, 0)))), ISNUMBER(SEARCH(A13, INDEX($F$25:$F$28, MATCH(C13, $C$25:$C$28, 0))))), COUNTIFS('03_Raw_POS_Journal'!$F$5:$F$678, A13, '03_Raw_POS_Journal'!$G$5:$G$678, INDEX($A$25:$A$28, MATCH(C13, $C$25:$C$28, 0))), 0) | M13: =IF(L13>=10, "HIGH CONCURRENCY", IF(L13>=3, "WATCHLIST", "STANDARD"))
A14: C-109 | B14: =IFERROR(VLOOKUP(A14, '02_Cashier_Register'!$A$14:$G$28, 2, FALSE), "Unknown") | C14: =IFERROR(VLOOKUP(A14, '02_Cashier_Register'!$A$14:$G$28, 3, FALSE), "Unknown") | D14: =COUNTIFS('03_Raw_POS_Journal'!$F$5:$F$678, A14, '03_Raw_POS_Journal'!$H$5:$H$678, "Line Item Void") | E14: =COUNTIFS('03_Raw_POS_Journal'!$F$5:$F$678, A14, '03_Raw_POS_Journal'!$H$5:$H$678, "Line Item Void", '03_Raw_POS_Journal'!$I$5:$I$678, "Cash") | F14: =SUMIFS('03_Raw_POS_Journal'!$K$5:$K$678, '03_Raw_POS_Journal'!$F$5:$F$678, A14, '03_Raw_POS_Journal'!$H$5:$H$678, "Line Item Void") | G14: =SUMIFS('03_Raw_POS_Journal'!$K$5:$K$678, '03_Raw_POS_Journal'!$F$5:$F$678, A14, '03_Raw_POS_Journal'!$H$5:$H$678, "Line Item Void", '03_Raw_POS_Journal'!$I$5:$I$678, "Cash") | H14: =IFERROR(IF(D14>0, E14/D14, 0), 0) | I14: =IFERROR(IF(_xlfn.STDEV.S($E$6:$E$20)=0, 0, (E14 - AVERAGE($E$6:$E$20)) / _xlfn.STDEV.S($E$6:$E$20)), 0) | J14: =IF(I14>=2.0, "HIGH RISK", IF(I14>=1.0, "ELEVATED RISK", "STANDARD")) | K14: =COUNTIFS('03_Raw_POS_Journal'!$F$5:$F$678, A14, '03_Raw_POS_Journal'!$G$5:$G$678, "<>NONE") | L14: =IF(AND(ISNUMBER(SEARCH("COLLUSION", INDEX($I$25:$I$28, MATCH(C14, $C$25:$C$28, 0)))), ISNUMBER(SEARCH(A14, INDEX($F$25:$F$28, MATCH(C14, $C$25:$C$28, 0))))), COUNTIFS('03_Raw_POS_Journal'!$F$5:$F$678, A14, '03_Raw_POS_Journal'!$G$5:$G$678, INDEX($A$25:$A$28, MATCH(C14, $C$25:$C$28, 0))), 0) | M14: =IF(L14>=10, "HIGH CONCURRENCY", IF(L14>=3, "WATCHLIST", "STANDARD"))
A15: C-110 | B15: =IFERROR(VLOOKUP(A15, '02_Cashier_Register'!$A$14:$G$28, 2, FALSE), "Unknown") | C15: =IFERROR(VLOOKUP(A15, '02_Cashier_Register'!$A$14:$G$28, 3, FALSE), "Unknown") | D15: =COUNTIFS('03_Raw_POS_Journal'!$F$5:$F$678, A15, '03_Raw_POS_Journal'!$H$5:$H$678, "Line Item Void") | E15: =COUNTIFS('03_Raw_POS_Journal'!$F$5:$F$678, A15, '03_Raw_POS_Journal'!$H$5:$H$678, "Line Item Void", '03_Raw_POS_Journal'!$I$5:$I$678, "Cash") | F15: =SUMIFS('03_Raw_POS_Journal'!$K$5:$K$678, '03_Raw_POS_Journal'!$F$5:$F$678, A15, '03_Raw_POS_Journal'!$H$5:$H$678, "Line Item Void") | G15: =SUMIFS('03_Raw_POS_Journal'!$K$5:$K$678, '03_Raw_POS_Journal'!$F$5:$F$678, A15, '03_Raw_POS_Journal'!$H$5:$H$678, "Line Item Void", '03_Raw_POS_Journal'!$I$5:$I$678, "Cash") | H15: =IFERROR(IF(D15>0, E15/D15, 0), 0) | I15: =IFERROR(IF(_xlfn.STDEV.S($E$6:$E$20)=0, 0, (E15 - AVERAGE($E$6:$E$20)) / _xlfn.STDEV.S($E$6:$E$20)), 0) | J15: =IF(I15>=2.0, "HIGH RISK", IF(I15>=1.0, "ELEVATED RISK", "STANDARD")) | K15: =COUNTIFS('03_Raw_POS_Journal'!$F$5:$F$678, A15, '03_Raw_POS_Journal'!$G$5:$G$678, "<>NONE") | L15: =IF(AND(ISNUMBER(SEARCH("COLLUSION", INDEX($I$25:$I$28, MATCH(C15, $C$25:$C$28, 0)))), ISNUMBER(SEARCH(A15, INDEX($F$25:$F$28, MATCH(C15, $C$25:$C$28, 0))))), COUNTIFS('03_Raw_POS_Journal'!$F$5:$F$678, A15, '03_Raw_POS_Journal'!$G$5:$G$678, INDEX($A$25:$A$28, MATCH(C15, $C$25:$C$28, 0))), 0) | M15: =IF(L15>=10, "HIGH CONCURRENCY", IF(L15>=3, "WATCHLIST", "STANDARD"))
A16: C-111 | B16: =IFERROR(VLOOKUP(A16, '02_Cashier_Register'!$A$14:$G$28, 2, FALSE), "Unknown") | C16: =IFERROR(VLOOKUP(A16, '02_Cashier_Register'!$A$14:$G$28, 3, FALSE), "Unknown") | D16: =COUNTIFS('03_Raw_POS_Journal'!$F$5:$F$678, A16, '03_Raw_POS_Journal'!$H$5:$H$678, "Line Item Void") | E16: =COUNTIFS('03_Raw_POS_Journal'!$F$5:$F$678, A16, '03_Raw_POS_Journal'!$H$5:$H$678, "Line Item Void", '03_Raw_POS_Journal'!$I$5:$I$678, "Cash") | F16: =SUMIFS('03_Raw_POS_Journal'!$K$5:$K$678, '03_Raw_POS_Journal'!$F$5:$F$678, A16, '03_Raw_POS_Journal'!$H$5:$H$678, "Line Item Void") | G16: =SUMIFS('03_Raw_POS_Journal'!$K$5:$K$678, '03_Raw_POS_Journal'!$F$5:$F$678, A16, '03_Raw_POS_Journal'!$H$5:$H$678, "Line Item Void", '03_Raw_POS_Journal'!$I$5:$I$678, "Cash") | H16: =IFERROR(IF(D16>0, E16/D16, 0), 0) | I16: =IFERROR(IF(_xlfn.STDEV.S($E$6:$E$20)=0, 0, (E16 - AVERAGE($E$6:$E$20)) / _xlfn.STDEV.S($E$6:$E$20)), 0) | J16: =IF(I16>=2.0, "HIGH RISK", IF(I16>=1.0, "ELEVATED RISK", "STANDARD")) | K16: =COUNTIFS('03_Raw_POS_Journal'!$F$5:$F$678, A16, '03_Raw_POS_Journal'!$G$5:$G$678, "<>NONE") | L16: =IF(AND(ISNUMBER(SEARCH("COLLUSION", INDEX($I$25:$I$28, MATCH(C16, $C$25:$C$28, 0)))), ISNUMBER(SEARCH(A16, INDEX($F$25:$F$28, MATCH(C16, $C$25:$C$28, 0))))), COUNTIFS('03_Raw_POS_Journal'!$F$5:$F$678, A16, '03_Raw_POS_Journal'!$G$5:$G$678, INDEX($A$25:$A$28, MATCH(C16, $C$25:$C$28, 0))), 0) | M16: =IF(L16>=10, "HIGH CONCURRENCY", IF(L16>=3, "WATCHLIST", "STANDARD"))
A17: C-112 | B17: =IFERROR(VLOOKUP(A17, '02_Cashier_Register'!$A$14:$G$28, 2, FALSE), "Unknown") | C17: =IFERROR(VLOOKUP(A17, '02_Cashier_Register'!$A$14:$G$28, 3, FALSE), "Unknown") | D17: =COUNTIFS('03_Raw_POS_Journal'!$F$5:$F$678, A17, '03_Raw_POS_Journal'!$H$5:$H$678, "Line Item Void") | E17: =COUNTIFS('03_Raw_POS_Journal'!$F$5:$F$678, A17, '03_Raw_POS_Journal'!$H$5:$H$678, "Line Item Void", '03_Raw_POS_Journal'!$I$5:$I$678, "Cash") | F17: =SUMIFS('03_Raw_POS_Journal'!$K$5:$K$678, '03_Raw_POS_Journal'!$F$5:$F$678, A17, '03_Raw_POS_Journal'!$H$5:$H$678, "Line Item Void") | G17: =SUMIFS('03_Raw_POS_Journal'!$K$5:$K$678, '03_Raw_POS_Journal'!$F$5:$F$678, A17, '03_Raw_POS_Journal'!$H$5:$H$678, "Line Item Void", '03_Raw_POS_Journal'!$I$5:$I$678, "Cash") | H17: =IFERROR(IF(D17>0, E17/D17, 0), 0) | I17: =IFERROR(IF(_xlfn.STDEV.S($E$6:$E$20)=0, 0, (E17 - AVERAGE($E$6:$E$20)) / _xlfn.STDEV.S($E$6:$E$20)), 0) | J17: =IF(I17>=2.0, "HIGH RISK", IF(I17>=1.0, "ELEVATED RISK", "STANDARD")) | K17: =COUNTIFS('03_Raw_POS_Journal'!$F$5:$F$678, A17, '03_Raw_POS_Journal'!$G$5:$G$678, "<>NONE") | L17: =IF(AND(ISNUMBER(SEARCH("COLLUSION", INDEX($I$25:$I$28, MATCH(C17, $C$25:$C$28, 0)))), ISNUMBER(SEARCH(A17, INDEX($F$25:$F$28, MATCH(C17, $C$25:$C$28, 0))))), COUNTIFS('03_Raw_POS_Journal'!$F$5:$F$678, A17, '03_Raw_POS_Journal'!$G$5:$G$678, INDEX($A$25:$A$28, MATCH(C17, $C$25:$C$28, 0))), 0) | M17: =IF(L17>=10, "HIGH CONCURRENCY", IF(L17>=3, "WATCHLIST", "STANDARD"))
... A20: C-115 | B20: =IFERROR(VLOOKUP(A20, '02_Cashier_Register'!$A$14:$G$28, 2, FALSE), "Unknown") | C20: =IFERROR(VLOOKUP(A20, '02_Cashier_Register'!$A$14:$G$28, 3, FALSE), "Unknown") | D20: =COUNTIFS('03_Raw_POS_Journal'!$F$5:$F$678, A20, '03_Raw_POS_Journal'!$H$5:$H$678, "Line Item Void") | E20: =COUNTIFS('03_Raw_POS_Journal'!$F$5:$F$678, A20, '03_Raw_POS_Journal'!$H$5:$H$678, "Line Item Void", '03_Raw_POS_Journal'!$I$5:$I$678, "Cash") | F20: =SUMIFS('03_Raw_POS_Journal'!$K$5:$K$678, '03_Raw_POS_Journal'!$F$5:$F$678, A20, '03_Raw_POS_Journal'!$H$5:$H$678, "Line Item Void") | G20: =SUMIFS('03_Raw_POS_Journal'!$K$5:$K$678, '03_Raw_POS_Journal'!$F$5:$F$678, A20, '03_Raw_POS_Journal'!$H$5:$H$678, "Line Item Void", '03_Raw_POS_Journal'!$I$5:$I$678, "Cash") | H20: =IFERROR(IF(D20>0, E20/D20, 0), 0) | I20: =IFERROR(IF(_xlfn.STDEV.S($E$6:$E$20)=0, 0, (E20 - AVERAGE($E$6:$E$20)) / _xlfn.STDEV.S($E$6:$E$20)), 0) | J20: =IF(I20>=2.0, "HIGH RISK", IF(I20>=1.0, "ELEVATED RISK", "STANDARD")) | K20: =COUNTIFS('03_Raw_POS_Journal'!$F$5:$F$678, A20, '03_Raw_POS_Journal'!$G$5:$G$678, "<>NONE") | L20: =IF(AND(ISNUMBER(SEARCH("COLLUSION", INDEX($I$25:$I$28, MATCH(C20, $C$25:$C$28, 0)))), ISNUMBER(SEARCH(A20, INDEX($F$25:$F$28, MATCH(C20, $C$25:$C$28, 0))))), COUNTIFS('03_Raw_POS_Journal'!$F$5:$F$678, A20, '03_Raw_POS_Journal'!$G$5:$G$678, INDEX($A$25:$A$28, MATCH(C20, $C$25:$C$28, 0))), 0) | M20: =IF(L20>=10, "HIGH CONCURRENCY", IF(L20>=3, "WATCHLIST", "STANDARD"))
A23: PART 2: SUPERVISOR PIN UTILIZATION & CONCURRENCY AUDIT
A24: Supervisor PIN | B24: Supervisor Name | C24: Assigned Branch | D24: Total Overrides Authorized | E24: Unique Cashiers Approved | F24: Primary Beneficiary Cashier | G24: Approvals on Primary Cashier | H24: Concentration % | I24: Credential Concurrency Status
A25: M-901 | B25: Robert Hughes | C25: BR-01 | D25: =COUNTIF('03_Raw_POS_Journal'!$G$5:$G$678, "M-901") | E25: 3 | F25: Kevin O'Connor (C-104) | G25: =COUNTIFS('03_Raw_POS_Journal'!$G$5:$G$678, "M-901", '03_Raw_POS_Journal'!$F$5:$F$678, "C-104") | H25: =IFERROR(IF(D25>0, G25/D25, 0), 0) | I25: STANDARD
A26: M-902 | B26: Nadia Cherkaoui | C26: BR-02 | D26: =COUNTIF('03_Raw_POS_Journal'!$G$5:$G$678, "M-902") | E26: 3 | F26: Jason Miller (C-108) | G26: =COUNTIFS('03_Raw_POS_Journal'!$G$5:$G$678, "M-902", '03_Raw_POS_Journal'!$F$5:$F$678, "C-108") | H26: =IFERROR(IF(D26>0, G26/D26, 0), 0) | I26: STANDARD
A27: M-903 | B27: Viktor Lindqvist | C27: BR-03 | D27: =COUNTIF('03_Raw_POS_Journal'!$G$5:$G$678, "M-903") | E27: 3 | F27: Ahmed Hassan (C-110) | G27: =COUNTIFS('03_Raw_POS_Journal'!$G$5:$G$678, "M-903", '03_Raw_POS_Journal'!$F$5:$F$678, "C-110") | H27: =IFERROR(IF(D27>0, G27/D27, 0), 0) | I27: STANDARD
A28: M-904 | B28: Darren Cooper | C28: BR-04 | D28: =COUNTIF('03_Raw_POS_Journal'!$G$5:$G$678, "M-904") | E28: 2 | F28: Samantha Reed (C-115) | G28: =COUNTIFS('03_Raw_POS_Journal'!$G$5:$G$678, "M-904", '03_Raw_POS_Journal'!$F$5:$F$678, "C-115") | H28: =IFERROR(IF(D28>0, G28/D28, 0), 0) | I28: COLLUSION RISK: SIMULTANEOUS PIN USE

Sheet 99_Investigator_Dashboard
A1: INTERNAL AUDIT & LOSS PREVENTION INVESTIGATION DASHBOARD
A2: EXECUTIVE SUMMARY: Cashier exception heatmap, quantified cash exposure, and targeted surveillance review queue prioritized for field investigation.
A4: TOTAL EVENTS AUDITED | C4: CASHIERS EVALUATED | E4: EXCEPTIONS FLAGGED | G4: QUANTIFIED EXPOSURE | I4: TARGET VIDEO REVIEW (HRS)
A5: =COUNTA('03_Raw_POS_Journal'!$A$5:$A$678) | C5: =COUNTA('02_Cashier_Register'!$A$14:$A$28) | E5: =COUNTIF($E$12:$E$26, "CRITICAL") + COUNTIF($E$12:$E$26, "HIGH") + COUNTIF($E$12:$E$26, "*COLLUSION*") | G5: =SUM($G$12:$G$26) | I5: =ROUNDUP(SUM($H$12:$H$26)*10/60, 1)
A6: Total raw POS transactions processed across all terminals | C6: Active cashiers evaluated against peer and branch baselines | E6: Cashiers exceeding composite risk thresholds or collusion parameters | G6: Estimated cash exposure from voids, drops, and unrecorded openings | I6: Targeted surveillance review hours required for corroboration
A10: CASHIER EXCEPTION HEATMAP & COMPOSITE RISK INDEX (RANKED BY COMPOSITE SCORE)
A11: Cashier ID | B11: Cashier Name | C11: Branch | D11: Composite Risk Score (0-100) | E11: Risk Classification | F11: Primary Exception Mode | G11: Quantified Exposure ($) | H11: Priority Exception Count | I11: Recommended Audit Action
A12: C-101 | B12: =IFERROR(VLOOKUP(A12, '02_Cashier_Register'!$A$14:$G$28, 2, FALSE), "Unknown") | C12: =IFERROR(VLOOKUP(A12, '02_Cashier_Register'!$A$14:$G$28, 3, FALSE), "Unknown") | D12: =MIN(100, ROUND(('04_Engine_Voids'!K5 * 5.0) + ('05_Engine_Drawer_Kicks'!H5 * 2.2) + ('06_Engine_Overrides'!E6 * 2.5) + ('06_Engine_Overrides'!L6 * 5.0), 0)) | E12: =IF('06_Engine_Overrides'!L6>=10, "WATCHLIST / HIGH COLLUSION", IF(D12>=70, "CRITICAL", IF(D12>=40, "HIGH", IF(D12>=20, "ELEVATED", "LOW")))) | F12: Standard operational variation | G12: ='04_Engine_Voids'!L5 + '05_Engine_Drawer_Kicks'!J5 + '06_Engine_Overrides'!G6 | H12: ='04_Engine_Voids'!K5 + ROUND('05_Engine_Drawer_Kicks'!H5/5, 0) + '06_Engine_Overrides'!E6 + '06_Engine_Overrides'!L6 | I12: Routine monitoring; no exception escalation required.
A13: C-102 | B13: =IFERROR(VLOOKUP(A13, '02_Cashier_Register'!$A$14:$G$28, 2, FALSE), "Unknown") | C13: =IFERROR(VLOOKUP(A13, '02_Cashier_Register'!$A$14:$G$28, 3, FALSE), "Unknown") | D13: =MIN(100, ROUND(('04_Engine_Voids'!K6 * 5.0) + ('05_Engine_Drawer_Kicks'!H6 * 2.2) + ('06_Engine_Overrides'!E7 * 2.5) + ('06_Engine_Overrides'!L7 * 5.0), 0)) | E13: =IF('06_Engine_Overrides'!L7>=10, "WATCHLIST / HIGH COLLUSION", IF(D13>=70, "CRITICAL", IF(D13>=40, "HIGH", IF(D13>=20, "ELEVATED", "LOW")))) | F13: Standard operational variation | G13: ='04_Engine_Voids'!L6 + '05_Engine_Drawer_Kicks'!J6 + '06_Engine_Overrides'!G7 | H13: ='04_Engine_Voids'!K6 + ROUND('05_Engine_Drawer_Kicks'!H6/5, 0) + '06_Engine_Overrides'!E7 + '06_Engine_Overrides'!L7 | I13: Routine monitoring; no exception escalation required.
A14: C-103 | B14: =IFERROR(VLOOKUP(A14, '02_Cashier_Register'!$A$14:$G$28, 2, FALSE), "Unknown") | C14: =IFERROR(VLOOKUP(A14, '02_Cashier_Register'!$A$14:$G$28, 3, FALSE), "Unknown") | D14: =MIN(100, ROUND(('04_Engine_Voids'!K7 * 5.0) + ('05_Engine_Drawer_Kicks'!H7 * 2.2) + ('06_Engine_Overrides'!E8 * 2.5) + ('06_Engine_Overrides'!L8 * 5.0), 0)) | E14: =IF('06_Engine_Overrides'!L8>=10, "WATCHLIST / HIGH COLLUSION", IF(D14>=70, "CRITICAL", IF(D14>=40, "HIGH", IF(D14>=20, "ELEVATED", "LOW")))) | F14: Standard operational variation | G14: ='04_Engine_Voids'!L7 + '05_Engine_Drawer_Kicks'!J7 + '06_Engine_Overrides'!G8 | H14: ='04_Engine_Voids'!K7 + ROUND('05_Engine_Drawer_Kicks'!H7/5, 0) + '06_Engine_Overrides'!E8 + '06_Engine_Overrides'!L8 | I14: Routine monitoring; no exception escalation required.
A15: C-104 | B15: =IFERROR(VLOOKUP(A15, '02_Cashier_Register'!$A$14:$G$28, 2, FALSE), "Unknown") | C15: =IFERROR(VLOOKUP(A15, '02_Cashier_Register'!$A$14:$G$28, 3, FALSE), "Unknown") | D15: =MIN(100, ROUND(('04_Engine_Voids'!K8 * 5.0) + ('05_Engine_Drawer_Kicks'!H8 * 2.2) + ('06_Engine_Overrides'!E9 * 2.5) + ('06_Engine_Overrides'!L9 * 5.0), 0)) | E15: =IF('06_Engine_Overrides'!L9>=10, "WATCHLIST / HIGH COLLUSION", IF(D15>=70, "CRITICAL", IF(D15>=40, "HIGH", IF(D15>=20, "ELEVATED", "LOW")))) | F15: Post-Settlement Cash Voids (Latency >180s) | G15: ='04_Engine_Voids'!L8 + '05_Engine_Drawer_Kicks'!J8 + '06_Engine_Overrides'!G9 | H15: ='04_Engine_Voids'!K8 + ROUND('05_Engine_Drawer_Kicks'!H8/5, 0) + '06_Engine_Overrides'!E9 + '06_Engine_Overrides'!L9 | I15: Review overhead surveillance for 16 cash void timestamps; verify customer departure prior to cancellation.
A16: C-105 | B16: =IFERROR(VLOOKUP(A16, '02_Cashier_Register'!$A$14:$G$28, 2, FALSE), "Unknown") | C16: =IFERROR(VLOOKUP(A16, '02_Cashier_Register'!$A$14:$G$28, 3, FALSE), "Unknown") | D16: =MIN(100, ROUND(('04_Engine_Voids'!K9 * 5.0) + ('05_Engine_Drawer_Kicks'!H9 * 2.2) + ('06_Engine_Overrides'!E10 * 2.5) + ('06_Engine_Overrides'!L10 * 5.0), 0)) | E16: =IF('06_Engine_Overrides'!L10>=10, "WATCHLIST / HIGH COLLUSION", IF(D16>=70, "CRITICAL", IF(D16>=40, "HIGH", IF(D16>=20, "ELEVATED", "LOW")))) | F16: Standard operational variation | G16: ='04_Engine_Voids'!L9 + '05_Engine_Drawer_Kicks'!J9 + '06_Engine_Overrides'!G10 | H16: ='04_Engine_Voids'!K9 + ROUND('05_Engine_Drawer_Kicks'!H9/5, 0) + '06_Engine_Overrides'!E10 + '06_Engine_Overrides'!L10 | I16: Routine monitoring; no exception escalation required.
A17: C-106 | B17: =IFERROR(VLOOKUP(A17, '02_Cashier_Register'!$A$14:$G$28, 2, FALSE), "Unknown") | C17: =IFERROR(VLOOKUP(A17, '02_Cashier_Register'!$A$14:$G$28, 3, FALSE), "Unknown") | D17: =MIN(100, ROUND(('04_Engine_Voids'!K10 * 5.0) + ('05_Engine_Drawer_Kicks'!H10 * 2.2) + ('06_Engine_Overrides'!E11 * 2.5) + ('06_Engine_Overrides'!L11 * 5.0), 0)) | E17: =IF('06_Engine_Overrides'!L11>=10, "WATCHLIST / HIGH COLLUSION", IF(D17>=70, "CRITICAL", IF(D17>=40, "HIGH", IF(D17>=20, "ELEVATED", "LOW")))) | F17: Standard operational variation | G17: ='04_Engine_Voids'!L10 + '05_Engine_Drawer_Kicks'!J10 + '06_Engine_Overrides'!G11 | H17: ='04_Engine_Voids'!K10 + ROUND('05_Engine_Drawer_Kicks'!H10/5, 0) + '06_Engine_Overrides'!E11 + '06_Engine_Overrides'!L11 | I17: Routine monitoring; no exception escalation required.
A18: C-107 | B18: =IFERROR(VLOOKUP(A18, '02_Cashier_Register'!$A$14:$G$28, 2, FALSE), "Unknown") | C18: =IFERROR(VLOOKUP(A18, '02_Cashier_Register'!$A$14:$G$28, 3, FALSE), "Unknown") | D18: =MIN(100, ROUND(('04_Engine_Voids'!K11 * 5.0) + ('05_Engine_Drawer_Kicks'!H11 * 2.2) + ('06_Engine_Overrides'!E12 * 2.5) + ('06_Engine_Overrides'!L12 * 5.0), 0)) | E18: =IF('06_Engine_Overrides'!L12>=10, "WATCHLIST / HIGH COLLUSION", IF(D18>=70, "CRITICAL", IF(D18>=40, "HIGH", IF(D18>=20, "ELEVATED", "LOW")))) | F18: Standard operational variation | G18: ='04_Engine_Voids'!L11 + '05_Engine_Drawer_Kicks'!J11 + '06_Engine_Overrides'!G12 | H18: ='04_Engine_Voids'!K11 + ROUND('05_Engine_Drawer_Kicks'!H11/5, 0) + '06_Engine_Overrides'!E12 + '06_Engine_Overrides'!L12 | I18: Routine monitoring; no exception escalation required.
A19: C-108 | B19: =IFERROR(VLOOKUP(A19, '02_Cashier_Register'!$A$14:$G$28, 2, FALSE), "Unknown") | C19: =IFERROR(VLOOKUP(A19, '02_Cashier_Register'!$A$14:$G$28, 3, FALSE), "Unknown") | D19: =MIN(100, ROUND(('04_Engine_Voids'!K12 * 5.0) + ('05_Engine_Drawer_Kicks'!H12 * 2.2) + ('06_Engine_Overrides'!E13 * 2.5) + ('06_Engine_Overrides'!L13 * 5.0), 0)) | E19: =IF('06_Engine_Overrides'!L13>=10, "WATCHLIST / HIGH COLLUSION", IF(D19>=70, "CRITICAL", IF(D19>=40, "HIGH", IF(D19>=20, "ELEVATED", "LOW")))) | F19: Pre-Settlement Line Item Deletions (Cash Tenders) | G19: ='04_Engine_Voids'!L12 + '05_Engine_Drawer_Kicks'!J12 + '06_Engine_Overrides'!G13 | H19: ='04_Engine_Voids'!K12 + ROUND('05_Engine_Drawer_Kicks'!H12/5, 0) + '06_Engine_Overrides'!E13 + '06_Engine_Overrides'!L13 | I19: Inspect terminal itemization vs guest receipt for high-value menu items.
A20: C-109 | B20: =IFERROR(VLOOKUP(A20, '02_Cashier_Register'!$A$14:$G$28, 2, FALSE), "Unknown") | C20: =IFERROR(VLOOKUP(A20, '02_Cashier_Register'!$A$14:$G$28, 3, FALSE), "Unknown") | D20: =MIN(100, ROUND(('04_Engine_Voids'!K13 * 5.0) + ('05_Engine_Drawer_Kicks'!H13 * 2.2) + ('06_Engine_Overrides'!E14 * 2.5) + ('06_Engine_Overrides'!L14 * 5.0), 0)) | E20: =IF('06_Engine_Overrides'!L14>=10, "WATCHLIST / HIGH COLLUSION", IF(D20>=70, "CRITICAL", IF(D20>=40, "HIGH", IF(D20>=20, "ELEVATED", "LOW")))) | F20: Standard operational variation | G20: ='04_Engine_Voids'!L13 + '05_Engine_Drawer_Kicks'!J13 + '06_Engine_Overrides'!G14 | H20: ='04_Engine_Voids'!K13 + ROUND('05_Engine_Drawer_Kicks'!H13/5, 0) + '06_Engine_Overrides'!E14 + '06_Engine_Overrides'!L14 | I20: Routine monitoring; no exception escalation required.
A21: C-110 | B21: =IFERROR(VLOOKUP(A21, '02_Cashier_Register'!$A$14:$G$28, 2, FALSE), "Unknown") | C21: =IFERROR(VLOOKUP(A21, '02_Cashier_Register'!$A$14:$G$28, 3, FALSE), "Unknown") | D21: =MIN(100, ROUND(('04_Engine_Voids'!K14 * 5.0) + ('05_Engine_Drawer_Kicks'!H14 * 2.2) + ('06_Engine_Overrides'!E15 * 2.5) + ('06_Engine_Overrides'!L15 * 5.0), 0)) | E21: =IF('06_Engine_Overrides'!L15>=10, "WATCHLIST / HIGH COLLUSION", IF(D21>=70, "CRITICAL", IF(D21>=40, "HIGH", IF(D21>=20, "ELEVATED", "LOW")))) | F21: Standard operational variation | G21: ='04_Engine_Voids'!L14 + '05_Engine_Drawer_Kicks'!J14 + '06_Engine_Overrides'!G15 | H21: ='04_Engine_Voids'!K14 + ROUND('05_Engine_Drawer_Kicks'!H14/5, 0) + '06_Engine_Overrides'!E15 + '06_Engine_Overrides'!L15 | I21: Routine monitoring; no exception escalation required.
A22: C-111 | B22: =IFERROR(VLOOKUP(A22, '02_Cashier_Register'!$A$14:$G$28, 2, FALSE), "Unknown") | C22: =IFERROR(VLOOKUP(A22, '02_Cashier_Register'!$A$14:$G$28, 3, FALSE), "Unknown") | D22: =MIN(100, ROUND(('04_Engine_Voids'!K15 * 5.0) + ('05_Engine_Drawer_Kicks'!H15 * 2.2) + ('06_Engine_Overrides'!E16 * 2.5) + ('06_Engine_Overrides'!L16 * 5.0), 0)) | E22: =IF('06_Engine_Overrides'!L16>=10, "WATCHLIST / HIGH COLLUSION", IF(D22>=70, "CRITICAL", IF(D22>=40, "HIGH", IF(D22>=20, "ELEVATED", "LOW")))) | F22: Standard operational variation | G22: ='04_Engine_Voids'!L15 + '05_Engine_Drawer_Kicks'!J15 + '06_Engine_Overrides'!G16 | H22: ='04_Engine_Voids'!K15 + ROUND('05_Engine_Drawer_Kicks'!H15/5, 0) + '06_Engine_Overrides'!E16 + '06_Engine_Overrides'!L16 | I22: Routine monitoring; no exception escalation required.
A23: C-112 | B23: =IFERROR(VLOOKUP(A23, '02_Cashier_Register'!$A$14:$G$28, 2, FALSE), "Unknown") | C23: =IFERROR(VLOOKUP(A23, '02_Cashier_Register'!$A$14:$G$28, 3, FALSE), "Unknown") | D23: =MIN(100, ROUND(('04_Engine_Voids'!K16 * 5.0) + ('05_Engine_Drawer_Kicks'!H16 * 2.2) + ('06_Engine_Overrides'!E17 * 2.5) + ('06_Engine_Overrides'!L17 * 5.0), 0)) | E23: =IF('06_Engine_Overrides'!L17>=10, "WATCHLIST / HIGH COLLUSION", IF(D23>=70, "CRITICAL", IF(D23>=40, "HIGH", IF(D23>=20, "ELEVATED", "LOW")))) | F23: Excessive No-Sale Drawer Openings during Peak Hours | G23: ='04_Engine_Voids'!L16 + '05_Engine_Drawer_Kicks'!J16 + '06_Engine_Overrides'!G17 | H23: ='04_Engine_Voids'!K16 + ROUND('05_Engine_Drawer_Kicks'!H16/5, 0) + '06_Engine_Overrides'!E17 + '06_Engine_Overrides'!L17 | I23: Perform unannounced drawer count during peak period; reconcile beverage physical inventory.
... A26: C-115 | B26: =IFERROR(VLOOKUP(A26, '02_Cashier_Register'!$A$14:$G$28, 2, FALSE), "Unknown") | C26: =IFERROR(VLOOKUP(A26, '02_Cashier_Register'!$A$14:$G$28, 3, FALSE), "Unknown") | D26: =MIN(100, ROUND(('04_Engine_Voids'!K19 * 5.0) + ('05_Engine_Drawer_Kicks'!H19 * 2.2) + ('06_Engine_Overrides'!E20 * 2.5) + ('06_Engine_Overrides'!L20 * 5.0), 0)) | E26: =IF('06_Engine_Overrides'!L20>=10, "WATCHLIST / HIGH COLLUSION", IF(D26>=70, "CRITICAL", IF(D26>=40, "HIGH", IF(D26>=20, "ELEVATED", "LOW")))) | F26: Supervisory PIN Concurrency & Rapid Cash Voids | G26: ='04_Engine_Voids'!L19 + '05_Engine_Drawer_Kicks'!J19 + '06_Engine_Overrides'!G20 | H26: ='04_Engine_Voids'!K19 + ROUND('05_Engine_Drawer_Kicks'!H19/5, 0) + '06_Engine_Overrides'!E20 + '06_Engine_Overrides'!L20 | I26: Review Manager M-904 override credentials; cross-reference terminal concurrency logs.
A29: TARGETED VIDEO SURVEILLANCE REVIEW QUEUE (FLAGGED INCIDENT TIMESTAMPS)
A30: Priority | B30: Incident Timestamp | C30: Branch | D30: Terminal | E30: Cashier ID | F30: Cashier Name | G30: Exception Category | H30: Dollar Value | I30: Camera Angle | J30: Audit Verification Objective
A31: HIGH-1 | B31: 2026-10-10 14:22:15 | C31: BR-01 | D31: T-02 | E31: C-104 | F31: Kevin O'Connor | G31: Post-Settlement Cash Void (Latency: 285s) | H31: 48.5 | I31: CAM-02 (Overhead Till) | J31: Verify whether customer tendered currency and departed counter prior to ticket cancellation.
A32: HIGH-2 | B32: 2026-10-11 18:45:10 | C32: BR-01 | D32: T-02 | E32: C-104 | F32: Kevin O'Connor | G32: Post-Settlement Cash Void (Latency: 310s) | H32: 52 | I32: CAM-02 (Overhead Till) | J32: Confirm whether supervisor M-901 was physically present at workstation during authorization.
A33: HIGH-3 | B33: 2026-10-12 13:12:44 | C33: BR-02 | D33: T-01 | E33: C-108 | F33: Jason Miller | G33: Pre-Settlement Line Item Deletion | H33: 42 | I33: CAM-01 (Counter & Hand-Off) | J33: Verify whether customer received full order while register record reflects only beverage item.
A34: HIGH-4 | B34: 2026-10-13 12:35:20 | C34: BR-03 | D34: T-02 | E34: C-112 | F34: Ryan Gallagher | G34: No-Sale Drawer Opening during Peak Period | H34: 0 | I34: CAM-03 (Cash Till Overhead) | J34: Determine whether currency was accepted and deposited into drawer without active ticket entry.
A35: HIGH-5 | B35: 2026-10-14 16:15:30 | C35: BR-04 | D35: T-02 | E35: C-115 | F35: Samantha Reed | G35: Supervisory Credential Concurrency (M-904) | H35: 38 | I35: CAM-01 & CAM-02 Split | J35: Verify physical location of M-904; terminal T-01 recorded separate override 22 seconds prior.
A36: HIGH-6 | B36: 2026-10-15 20:05:18 | C36: BR-01 | D36: T-02 | E36: C-104 | F36: Kevin O'Connor | G36: Post-Settlement Cash Void (Latency: 240s) | H36: 64 | I36: CAM-02 (Overhead Till) | J36: Confirm customer payment method and check whether guest receipt was retained by cashier.
A37: HIGH-7 | B37: 2026-10-16 19:30:45 | C37: BR-02 | D37: T-01 | E37: C-108 | F37: Jason Miller | G37: Pre-Settlement Line Item Deletion | H37: 36.5 | I37: CAM-01 (Counter & Hand-Off) | J37: Reconcile tender denomination accepted against change returned and items handed over counter.
